Workbook

Sheet 00_说明
A1: 用途 | B1: 说明
A2: 来源 | B2: 基于 Docs/玩法数值规范.md 当前数值口径生成。
A3: 编辑规则 | B3: 配置列可以手填；校验列可由公式计算，资产落地前需要检查 BP、价格、权重和开放波次。
A4: 当前已填 | B4: 属性价值、升级卡、饰品。
A5: 当前仅建表头 | B5: 武器主表、武器等级表、怪物主表、怪物波次池、波次、商店内容池、掉落奖励池、校验汇总。
A6: 注意 | B6: 本 Excel 是数值设计表，不代表已经写入 Unity 资产。

Sheet 参数参考
A1: 类型 | B1: 名称 | C1: 值1 | D1: 值2 | E1: 说明
A2: 升级卡稀有度BP | B2: Common | C2: 100 | E2: 允许约 10% 浮动
A3: 升级卡稀有度BP | B3: Rare | C3: 150 | E3: 允许约 10% 浮动
A4: 升级卡稀有度BP | B4: Epic | C4: 225 | E4: 允许约 10% 浮动
A5: 升级卡稀有度BP | B5: Legendary | C5: 350 | E5: 允许约 10% 浮动
A6: 饰品品质BP | B6: Common | C6: 60 | D6: 110 | E6: 参考价 15-28 金币
A7: 饰品品质BP | B7: Rare | C7: 110 | D7: 180 | E7: 参考价 28-45 金币
A8: 饰品品质BP | B8: Epic | C8: 180 | D8: 280 | E8: 参考价 45-70 金币
A9: 饰品品质BP | B9: Legendary | C9: 280 | D9: 500 | E9: 参考价 70-125 金币
A10: 金币购买力 | B10: 1 金币 | C10: 4 | E10: 1 金币 = 4 BP

Sheet 01_属性价值
A1: 属性 | B1: 配置单位 | C1: 常规属性 | D1: 价值/点 | E1: 消费侧边界 | F1: 备注
A2: Attack | B2: 点数 | C2: 否 | D2: 40 | E2: 最终有效攻击不低于 0 | F2: 非常规升级卡属性，主要用于武器/饰品。
A3: Damage | B3: 百分比点 | C3: 是 | D3: 20 | E3: 最终伤害不低于 0 | F3: 通用输出锚点。
A4: MeleeAttack | B4: 点数 | C4: 是 | D4: 20 | E4: 最终武器伤害不低于 0 | F4: 受武器收益率影响。
A5: RangedAttack | B5: 点数 | C5: 是 | D5: 20 | E5: 最终武器伤害不低于 0 | F5: 受武器收益率影响。
A6: MagicAttack | B6: 点数 | C6: 是 | D6: 20 | E6: 最终武器伤害不低于 0 | F6: 受武器收益率影响。
A7: SummonAttack | B7: 点数 | C7: 是 | D7: 20 | E7: 最终武器伤害不低于 0 | F7: 受武器收益率影响。
A8: AttackSpeed | B8: 攻速点 | C8: 是 | D8: 20 | E8: 最终有效攻击速度不低于 1 | F8: 高频触发武器需靠收益率限制。
A9: CriticalChance | B9: 百分比点 | C9: 是 | D9: 50 | E9: 0%-100% | F9: 乘法入口，权重保守。
A10: CriticalPercent | B10: 百分比点 | C10: 是 | D10: 12 | E10: 最终暴击倍率不低于 1x | F10: 后期暴击属性，前期低暴击率应折扣。
A11: MoveSpeed | B11: 距离点/秒 | C11: 是 | D11: 10 | E11: 按局部最小值保护 | F11: 手感和走位属性。
A12: MaxHealth | B12: 点数 | C12: 是 | D12: 5 | E12: 最低为 1 | F12: 生命锚点。
A13: DetectionRange | B13: 距离点 | C13: 否 | E13: 当前无统一下限 | F13: 怪物/索敌配置。
A14: HealthRecoverySpeed | B14: 回复点 | C14: 是 | D14: 10 | E14: 最低为 0 | F14: 当前实战稳定性高于吸血。
A15: Armor | B15: 点数 | C15: 是 | D15: 80 | E15: 结算下限 -95，总减伤上限 95% | F15: 单点价值高。
A16: Luck | B16: 点数 | C16: 是 | D16: 20 | E16: 无统一边界 | F16: 同时影响奖励和商店权重。
A17: Dodge | B17: 百分比点 | C17: 是 | D17: 33 | E17: 有效 0%-50% | F17: 波动生存属性。
A18: LifeSteal | B18: 百分比点 | C18: 否 | D18: 20 | E18: 最低为 0 | F18: 当前实战低稳定性。
A19: PickupRadius | B19: 距离点 | C19: 否 | D19: 5 | E19: 最低为 0 | F19: 拾取效率属性。
A20: ProjectileSpeed | B20: 点数 | C20: 否 | D20: 5 | E20: 当前无统一下限 | F20: 投射物手感属性。
A21: AttackRange | B21: 距离点 | C21: 是 | D21: 8 | E21: 最终攻击距离不低于 0.1 格 | F21: 影响安全距离和覆盖。
A22: ProjectilePierceCount | B22: 点数 | C22: 否 | D22: 200 | E22: 最终不低于 0，向下取整 | F22: 机制入口。
A23: KnockbackStrength | B23: 点数 | C23: 否 | D23: 5 | E23: 最终不低于 0 | F23: 高频武器应保守。
A24: KnockbackResistance | B24: 百分比点 | C24: 否 | D24: 5 | E24: 0%-100% | F24: 怪物抗性属性。
A25: ExperienceGain | B25: 百分比点 | C25: 否 | D25: 15 | E25: 最低为 0 | F25: 越早越强。
... A30: WeaponSlotCount | B30: 点数 | C30: 否 | D30: 400 | E30: 不低于当前已装备槽位数 | F30: 终局构筑容量机制。

Sheet 02_升级卡
A1: 卡片ID | B1: 卡片族ID | C1: 显示名 | D1: 方向 | E1: 稀有度 | F1: 属性 | G1: 数值 | H1: 属性BP | I1: 条件修正 | J1: 修正后BP | K1: 稀有度目标BP | L1: BP偏差 | M1: 开放波次 | N1: 基础权重 | O1: 已选权重调整 | P1: 重复口径 | Q1: 备注
A2: Upgrade_Damage_Common | B2: Upgrade_Damage | C2: 伤害强化-普通 | D2: 输出 | E2: Common | F2: Damage | G2: 5 | H2: 100 | I2: 1 | J2: =H2*I2 -> 100 | K2: 100 | L2: =J2-K2 -> 0 | M2: 1+ | N2: 100 | O2: 0.95 | P2: 可重复 | Q2: 最通用输出卡，作为输出预算锚点。
A3: Upgrade_Damage_Rare | B3: Upgrade_Damage | C3: 伤害强化-稀有 | D3: 输出 | E3: Rare | F3: Damage | G3: 8 | H3: 160 | I3: 1 | J3: =H3*I3 -> 160 | K3: 150 | L3: =J3-K3 -> 10 | M3: 1+ | N3: 100 | O3: 0.95 | P3: 可重复 | Q3: 最通用输出卡，作为输出预算锚点。
A4: Upgrade_Damage_Epic | B4: Upgrade_Damage | C4: 伤害强化-史诗 | D4: 输出 | E4: Epic | F4: Damage | G4: 11 | H4: 220 | I4: 1 | J4: =H4*I4 -> 220 | K4: 225 | L4: =J4-K4 -> -5 | M4: 1+ | N4: 100 | O4: 0.95 | P4: 可重复 | Q4: 最通用输出卡，作为输出预算锚点。
A5: Upgrade_Damage_Legendary | B5: Upgrade_Damage | C5: 伤害强化-传说 | D5: 输出 | E5: Legendary | F5: Damage | G5: 17 | H5: 340 | I5: 1 | J5: =H5*I5 -> 340 | K5: 350 | L5: =J5-K5 -> -10 | M5: 1+ | N5: 100 | O5: 0.95 | P5: 可重复 | Q5: 最通用输出卡，作为输出预算锚点。
A6: Upgrade_AttackSpeed_Common | B6: Upgrade_AttackSpeed | C6: 攻速强化-普通 | D6: 输出 | E6: Common | F6: AttackSpeed | G6: 5 | H6: 100 | I6: 1 | J6: =H6*I6 -> 100 | K6: 100 | L6: =J6-K6 -> 0 | M6: 1+ | N6: 100 | O6: 0.95 | P6: 可重复 | Q6: 高频触发武器会放大该属性，依赖武器收益率限制。
A7: Upgrade_AttackSpeed_Rare | B7: Upgrade_AttackSpeed | C7: 攻速强化-稀有 | D7: 输出 | E7: Rare | F7: AttackSpeed | G7: 8 | H7: 160 | I7: 1 | J7: =H7*I7 -> 160 | K7: 150 | L7: =J7-K7 -> 10 | M7: 1+ | N7: 100 | O7: 0.95 | P7: 可重复 | Q7: 高频触发武器会放大该属性，依赖武器收益率限制。
A8: Upgrade_AttackSpeed_Epic | B8: Upgrade_AttackSpeed | C8: 攻速强化-史诗 | D8: 输出 | E8: Epic | F8: AttackSpeed | G8: 11 | H8: 220 | I8: 1 | J8: =H8*I8 -> 220 | K8: 225 | L8: =J8-K8 -> -5 | M8: 1+ | N8: 100 | O8: 0.95 | P8: 可重复 | Q8: 高频触发武器会放大该属性，依赖武器收益率限制。
A9: Upgrade_AttackSpeed_Legendary | B9: Upgrade_AttackSpeed | C9: 攻速强化-传说 | D9: 输出 | E9: Legendary | F9: AttackSpeed | G9: 17 | H9: 340 | I9: 1 | J9: =H9*I9 -> 340 | K9: 350 | L9: =J9-K9 -> -10 | M9: 1+ | N9: 100 | O9: 0.95 | P9: 可重复 | Q9: 高频触发武器会放大该属性，依赖武器收益率限制。
A10: Upgrade_MeleeAttack_Common | B10: Upgrade_MeleeAttack | C10: 近战训练-普通 | D10: 输出 | E10: Common | F10: MeleeAttack | G10: 5 | H10: 100 | I10: 1 | J10: =H10*I10 -> 100 | K10: 100 | L10: =J10-K10 -> 0 | M10: 1+ | N10: 85 | O10: 0.95 | P10: 可重复 | Q10: 四类攻击卡权重略低于通用输出卡。
A11: Upgrade_MeleeAttack_Rare | B11: Upgrade_MeleeAttack | C11: 近战训练-稀有 | D11: 输出 | E11: Rare | F11: MeleeAttack | G11: 8 | H11: 160 | I11: 1 | J11: =H11*I11 -> 160 | K11: 150 | L11: =J11-K11 -> 10 | M11: 1+ | N11: 85 | O11: 0.95 | P11: 可重复 | Q11: 四类攻击卡权重略低于通用输出卡。
A12: Upgrade_MeleeAttack_Epic | B12: Upgrade_MeleeAttack | C12: 近战训练-史诗 | D12: 输出 | E12: Epic | F12: MeleeAttack | G12: 11 | H12: 220 | I12: 1 | J12: =H12*I12 -> 220 | K12: 225 | L12: =J12-K12 -> -5 | M12: 1+ | N12: 85 | O12: 0.95 | P12: 可重复 | Q12: 四类攻击卡权重略低于通用输出卡。
A13: Upgrade_MeleeAttack_Legendary | B13: Upgrade_MeleeAttack | C13: 近战训练-传说 | D13: 输出 | E13: Legendary | F13: MeleeAttack | G13: 17 | H13: 340 | I13: 1 | J13: =H13*I13 -> 340 | K13: 350 | L13: =J13-K13 -> -10 | M13: 1+ | N13: 85 | O13: 0.95 | P13: 可重复 | Q13: 四类攻击卡权重略低于通用输出卡。
... A80: Upgrade_WaveGoldBonus_Legendary | B80: Upgrade_WaveGoldBonus | C80: 波次金币强化-传说 | D80: 经济 | E80: Legendary | F80: WaveGoldRewardBonus | G80: 28 | H80: 350 | I80: 1 | J80: =H80*I80 -> 350 | K80: 350 | L80: =J80-K80 -> 0 | M80: 1-10 | N80: 25 | O80: 0.8 | P80: 可重复 | Q80: 只适合前中期；10 波后价值明显下降。

Sheet 03_饰品
A1: 饰品ID | B1: 名称 | C1: 品质 | D1: 定位 | E1: 正向属性/机制 | F1: 正向BP | G1: 负向回收BP | H1: 机制BP | I1: 生存衰减 | J1: 最终BP | K1: 参考价 | L1: 实际价 | M1: 回收价 | N1: 重复口径 | O1: 入口 | P1: 开放波次 | Q1: 基础权重 | R1: 备注
A2: Accessory_C_DamageCharm | B2: 磨损力量护符 | C2: Common | D2: 通用输出 | E2: Damage +5 | F2: 100 | G2: 0 | H2: 0 | J2: 100 | K2: =ROUND(J2/4,0) -> 25 | L2: =K2 -> 25 | M2: =ROUND(L2*0.3,0) -> 8 | N2: 可重复 | O2: 商店 | P2: 1+ | Q2: 100 | R2: 最基础输出饰品。
A3: Accessory_C_LightTrigger | B3: 轻型扳机 | C3: Common | D3: 攻速 | E3: AttackSpeed +5 | F3: 100 | G3: 0 | H3: 0 | J3: 100 | K3: =ROUND(J3/4,0) -> 25 | L3: =K3 -> 25 | M3: =ROUND(L3*0.3,0) -> 8 | N3: 可重复 | O3: 商店 | P3: 1+ | Q3: 100 | R3: 高频武器收益受武器收益率限制。
A4: Accessory_C_PaddedVest | B4: 厚实护垫 | C4: Common | D4: 生命 | E4: MaxHealth +18 | F4: 90 | G4: 0 | H4: 0 | J4: 90 | K4: =ROUND(J4/4,0) -> 23 | L4: =K4 -> 23 | M4: =ROUND(L4*0.3,0) -> 7 | N4: 可重复 | O4: 商店 | P4: 1+ | Q4: 95 | R4: 低价生存入口。
A5: Accessory_C_FirstAidKit | B5: 简易药包 | C5: Common | D5: 回复 | E5: HealthRecoverySpeed +8 | F5: 80 | G5: 0 | H5: 0 | J5: 80 | K5: =ROUND(J5/4,0) -> 20 | L5: =K5 -> 20 | M5: =ROUND(L5*0.3,0) -> 6 | N5: 可重复 | O5: 商店 | P5: 1+ | Q5: 80 | R5: 回复体感强，Common 档不取满预算。
A6: Accessory_C_SpringLace | B6: 弹簧鞋带 | C6: Common | D6: 机动 | E6: MoveSpeed +8 | F6: 80 | G6: 0 | H6: 0 | J6: 80 | K6: =ROUND(J6/4,0) -> 20 | L6: =K6 -> 20 | M6: =ROUND(L6*0.3,0) -> 6 | N6: 可重复 | O6: 商店 | P6: 1+ | Q6: 80 | R6: 手感属性，低档投放。
A7: Accessory_C_MagnetRing | B7: 拾取磁环 | C7: Common | D7: 拾取 | E7: PickupRadius +18 | F7: 90 | G7: 0 | H7: 0 | J7: 90 | K7: =ROUND(J7/4,0) -> 23 | L7: =K7 -> 23 | M7: =ROUND(L7*0.3,0) -> 7 | N7: 可重复 | O7: 商店 | P7: 1+ | Q7: 75 | R7: 不直接提高战斗力，价格略低。
A8: Accessory_C_LuckyCoin | B8: 旧幸运币 | C8: Common | D8: 幸运 | E8: Luck +5 | F8: 100 | G8: 0 | H8: 0 | J8: 100 | K8: =ROUND(J8/4,0) -> 25 | L8: =K8 -> 25 | M8: =ROUND(L8*0.3,0) -> 8 | N8: 可重复 | O8: 商店 | P8: 1+ | Q8: 45 | R8: 经济入口，权重保守。
A9: Accessory_C_ShortScope | B9: 短距瞄具 | C9: Common | D9: 范围 | E9: AttackRange +12 | F9: 96 | G9: 0 | H9: 0 | J9: 96 | K9: =ROUND(J9/4,0) -> 24 | L9: =K9 -> 24 | M9: =ROUND(L9*0.3,0) -> 7 | N9: 可重复 | O9: 商店 | P9: 1+ | Q9: 70 | R9: 影响安全距离和命中覆盖。
A10: Accessory_C_MinorCritLens | B10: 裂纹准镜 | C10: Common | D10: 暴击 | E10: CriticalChance +1; CriticalPercent +4 | F10: 98 | G10: 0 | H10: 0 | J10: 98 | K10: =ROUND(J10/4,0) -> 25 | L10: =K10 -> 25 | M10: =ROUND(L10*0.3,0) -> 8 | N10: 可重复 | O10: 商店 | P10: 1+ | Q10: 65 | R10: 低阶精准入口，前期暴击率低时实际收益偏弱。
A11: Accessory_R_TacticalCore | B11: 战术核心 | C11: Rare | D11: 通用攻击 | E11: Attack +3 | F11: 120 | G11: 0 | H11: 0 | J11: 120 | K11: =ROUND(J11/4,0) -> 30 | L11: =K11 -> 30 | M11: =ROUND(L11*0.3,0) -> 9 | N11: 可重复 | O11: 商店 | P11: 3+ | Q11: 60 | R11: 全局基础攻击，投放比四类攻击更谨慎。
A12: Accessory_R_DamageManual | B12: 伤害手册 | C12: Rare | D12: 通用输出 | E12: Damage +8 | F12: 160 | G12: 0 | H12: 0 | J12: 160 | K12: =ROUND(J12/4,0) -> 40 | L12: =K12 -> 40 | M12: =ROUND(L12*0.3,0) -> 12 | N12: 可重复 | O12: 商店 | P12: 3+ | Q12: 85 | R12: Rare 标准输出件。
A13: Accessory_R_RapidGear | B13: 快速齿轮 | C13: Rare | D13: 攻速 | E13: AttackSpeed +8 | F13: 160 | G13: 0 | H13: 0 | J13: 160 | K13: =ROUND(J13/4,0) -> 40 | L13: =K13 -> 40 | M13: =ROUND(L13*0.3,0) -> 12 | N13: 可重复 | O13: 商店 | P13: 3+ | Q13: 85 | R13: 快速构筑入口。
... A22: Accessory_R_WavePurse | B22: 波次钱袋 | C22: Rare | D22: 金币 | E22: WaveGoldRewardBonus +12 | F22: 150 | G22: 0 | H22: 0 | J22: 150 | K22: =ROUND(J22/4,0) -> 38 | L22: =K22 -> 38 | M22: =ROUND(L22*0.3,0) -> 11 | N22: 可重复 | O22: 商店 | P22: 1-10 | Q22: 25 | R22: 越早越强，10 波后关闭。
A23: Accessory_R_FieldBandage | B23: 战地绷带 | C23: Rare | D23: 复合生存 | E23: MaxHealth +10; HealthRecoverySpeed +8 | F23: 130 | G23: 0 | H23: 0 | I23: 已保守控制 | J23: 130 | K23: =ROUND(J23/4,0) -> 33 | L23: =K23 -> 33 | M23: =ROUND(L23*0.3,0) -> 10 | N23: 可重复 | O23: 商店 | P23: 3+ | Q23: 65 | R23: 生命和回复的过渡件，避免早期纯回复过强。
A24: Accessory_R_LongBoots | B24: 长行军靴 | C24: Rare | D24: 机动范围 | E24: MoveSpeed +8; AttackRange +8 | F24: 144 | G24: 0 | H24: 0 | J24: 144 | K24: =ROUND(J24/4,0) -> 36 | L24: =K24 -> 36 | M24: =ROUND(L24*0.3,0) -> 11 | N24: 可重复 | O24: 商店 | P24: 3+ | Q24: 60 | R24: 兼顾走位和命中覆盖，不直接提高单次伤害。
A25: Accessory_R_CritPrimer | B25: 精密镜片 | C25: Rare | D25: 暴击 | E25: CriticalChance +2; CriticalPercent +4 | F25: 148 | G25: 0 | H25: 0 | J25: 148 | K25: =ROUND(J25/4,0) -> 37 | L25: =K25 -> 37 | M25: =ROUND(L25*0.3,0) -> 11 | N25: 可重复 | O25: 商店 | P25: 4+ | Q25: 55 | R25: 承接 Common 暴击件和 Epic 暴击构筑。
A26: Accessory_E_CritScope | B26: 暴击瞄准镜 | C26: Epic | D26: 暴击 | E26: CriticalChance +3; CriticalPercent +6 | F26: 222 | G26: 0 | H26: 0 | J26: 222 | K26: =ROUND(J26/4,0) -> 56 | L26: =K26 -> 56 | M26: =ROUND(L26*0.3,0) -> 17 | N26: 可重复 | O26: 商店 | P26: 6+ | Q26: 40 | R26: 精准构筑件，前期低暴击率时收益偏弱。
A27: Accessory_E_RegenCore | B27: 再生核心 | C27: Epic | D27: 回复 | E27: HealthRecoverySpeed +22 | F27: 220 | G27: 0 | H27: 0 | J27: 220 | K27: =ROUND(J27/4,0) -> 55 | L27: =K27 -> 55 | M27: =ROUND(L27*0.3,0) -> 17 | N27: 可重复 | O27: 商店 | P27: 6+ | Q27: 45 | R27: 强回复件，避免同件再叠高生命或高减伤。
A28: Accessory_E_CompositePlate | B28: 复合护板 | C28: Epic | D28: 复合生存 | E28: MaxHealth +24; DamageReduction +4 | F28: 220 | G28: 0 | H28: 0 | I28: 已保守控制 | J28: 220 | K28: =ROUND(J28/4,0) -> 55 | L28: =K28 -> 55 | M28: =ROUND(L28*0.3,0) -> 17 | N28: 可重复 | O28: 商店 | P28: 7+ | Q28: 35 | R28: 两条生存链路，已按保守值控制。
A29: Accessory_E_LongRangeStabilizer | B29: 远距稳定器 | C29: Epic | D29: 范围 | E29: AttackRange +28 | F29: 224 | G29: 0 | H29: 0 | J29: 224 | K29: =ROUND(J29/4,0) -> 56 | L29: =K29 -> 56 | M29: =ROUND(L29*0.3,0) -> 17 | N29: 可重复 | O29: 商店 | P29: 6+ | Q29: 45 | R29: 范围构筑件。
A30: Accessory_E_PiercingDrill | B30: 穿透钻头 | C30: Epic | D30: 穿透机制 | E30: ProjectilePierceCount +1 | F30: 0 | G30: 0 | H30: 200 | J30: 200 | K30: =ROUND(J30/4,0) -> 50 | L30: =K30 -> 50 | M30: =ROUND(L30*0.3,0) -> 15 | N30: 适量上限 2 | O30: 商店 | P30: 10+ | Q30: 18 | R30: 机制入口，不进入低品质。
A31: Accessory_E_FieldInstructor | B31: 战场教官 | C31: Epic | D31: 通用攻击 | E31: Attack +6 | F31: 240 | G31: 0 | H31: 0 | J31: 240 | K31: =ROUND(J31/4,0) -> 60 | L31: =K31 -> 60 | M31: =ROUND(L31*0.3,0) -> 18 | N31: 可重复 | O31: 商店 | P31: 8+ | Q31: 30 | R31: 全局基础攻击，高价值输出件。
A32: Accessory_E_GrowthLedger | B32: 成长账本 | C32: Epic | D32: 经济 | E32: ExperienceGain +12; Luck +4 | F32: 260 | G32: 0 | H32: 0 | J32: 260 | K32: =ROUND(J32/4,0) -> 65 | L32: =K32 -> 65 | M32: =ROUND(L32*0.3,0) -> 20 | N32: 可重复 | O32: 商店 | P32: 1-10 | Q32: 12 | R32: 早期经济构筑件，权重很低。
A33: Accessory_E_BalancedCore | B33: 均衡核心 | C33: Epic | D33: 复合输出 | E33: Damage +6; AttackSpeed +5 | F33: 220 | G33: 0 | H33: 0 | J33: 220 | K33: =ROUND(J33/4,0) -> 55 | L33: =K33 -> 55 | M33: =ROUND(L33*0.3,0) -> 17 | N33: 可重复 | O33: 商店 | P33: 6+ | Q33: 35 | R33: 稳定输出复合件，不额外附带乘区。
A34: Accessory_E_KnockbackCoil | B34: 击退线圈 | C34: Epic | D34: 控场 | E34: KnockbackStrength +40 | F34: 200 | G34: 0 | H34: 0 | J34: 200 | K34: =ROUND(J34/4,0) -> 50 | L34: =K34 -> 50 | M34: =ROUND(L34*0.3,0) -> 15 | N34: 可重复 | O34: 商店 | P34: 7+ | Q34: 25 | R34: 控场手感件，高频武器仍由武器收益率限制。
A35: Accessory_E_GuardianMantle | B35: 守护披肩 | C35: Epic | D35: 复合生存 | E35: Dodge +4; DamageReduction +3 | F35: 207 | G35: 0 | H35: 0 | I35: 已保守控制 | J35: 207 | K35: =ROUND(J35/4,0) -> 52 | L35: =K35 -> 52 | M35: =ROUND(L35*0.3,0) -> 16 | N35: 可重复 | O35: 商店 | P35: 8+ | Q35: 28 | R35: 闪避和减伤复合，按生存复合风险降低投放权重。
A36: Accessory_L_ExtraHolster | B36: 额外枪套 | C36: Legendary | D36: 武器槽机制 | E36: WeaponSlotCount +1 | F36: 0 | G36: 0 | H36: 400 | J36: 400 | K36: =ROUND(J36/4,0) -> 100 | L36: =K36 -> 100 | M36: =ROUND(L36*0.3,0) -> 30 | N36: 唯一 | O36: 商店; Boss 奖励 | P36: 15+ | Q36: 3 | R36: 终局构筑容量入口。
A37: Accessory_L_CritCrown | B37: 暴击王冠 | C37: Legendary | D37: 暴击 | E37: CriticalChance +5; CriticalPercent +12 | F37: 394 | G37: 0 | H37: 0 | J37: 394 | K37: =ROUND(J37/4,0) -> 99 | L37: =K37 -> 99 | M37: =ROUND(L37*0.3,0) -> 30 | N37: 可重复 | O37: 商店; Boss 奖励 | P37: 12+ | Q37: 8 | R37: 后期精准构筑核心。
A38: Accessory_L_AlloyTactics | B38: 合金战术板 | C38: Legendary | D38: 全类型攻击 | E38: Melee/Ranged/Magic/SummonAttack 各 +4 | F38: 320 | G38: 0 | H38: 0 | J38: 320 | K38: =ROUND(J38/4,0) -> 80 | L38: =K38 -> 80 | M38: =ROUND(L38*0.3,0) -> 24 | N38: 可重复 | O38: 商店 | P38: 12+ | Q38: 8 | R38: 多武器混合构筑件。
A39: Accessory_L_OverdriveCore | B39: 过载核心 | C39: Legendary | D39: 通用输出 | E39: Damage +15; AttackSpeed +4 | F39: 380 | G39: 0 | H39: 0 | J39: 380 | K39: =ROUND(J39/4,0) -> 95 | L39: =K39 -> 95 | M39: =ROUND(L39*0.3,0) -> 29 | N39: 可重复 | O39: 商店; Boss 奖励 | P39: 12+ | Q39: 8 | R39: 高输出复合件，不能再附带生存。
A40: Accessory_L_BenefitCoupler | B40: 收益耦合器 | C40: Legendary | D40: 武器收益率 | E40: AttackSpeedBenefit +5; CriticalChanceBenefit +2; RangeBenefit +5; 四类 Attack 收益率各 +2 | F40: 0 | G40: 0 | H40: 400 | J40: 400 | K40: =ROUND(J40/4,0) -> 100 | L40: =K40 -> 100 | M40: =ROUND(L40*0.3,0) -> 30 | N40: 适量上限 1 | O40: 商店; Boss 奖励 | P40: 14+ | Q40: 5 | R40: 放大外部属性，按全武器收益保守投放。
A41: Accessory_L_SurvivalMatrix | B41: 生存矩阵 | C41: Legendary | D41: 复合生存 | E41: MaxHealth +34; DamageReduction +7; HealthRecoverySpeed +10 | F41: 445 | G41: 0 | H41: 0 | I41: 已保守控制 | J41: 445 | K41: =ROUND(J41/4,0) -> 111 | L41: =K41 -> 111 | M41: =ROUND(L41*0.3,0) -> 33 | N41: 可重复 | O41: 商店; Boss 奖励 | P41: 12+ | Q41: 6 | R41: 高价值生存核心，靠传说品质和低权重限制可见性。

Sheet 04_武器主表
A1: 武器ID | B1: 名称 | C1: 品质 | D1: 主标签 | E1: 副标签 | F1: 定位 | G1: 基础开放波次 | H1: 基础权重 | I1: 1级价格 | J1: 1级总BP | K1: 目标价格偏差 | L1: 备注
A2: Weapon_IronHammer | B2: 铁锤 | C2: 正常武器 | D2: 重型 | E2: 近战 | F2: 低频高伤近战扫掠 | G2: 1+ | H2: 80 | I2: 25 | J2: 100 | K2: 0 | L2: 重型近战基准，单次命中强，攻速成长保守。
A3: Weapon_RapidSMG | B3: 冲锋枪 | C3: 正常武器 | D3: 快速 | E3: 远程 | F3: 高攻速低单发远程 | G3: 1+ | H3: 85 | I3: 25 | J3: 100 | K3: 0 | L3: 快速武器，击退和暴击收益率保守。
A4: Weapon_HuntingRifle | B4: 猎枪 | C4: 正常武器 | D4: 精准 | E4: 远程 | F4: 低频远程精准单体 | G4: 1+ | H4: 70 | I4: 28 | J4: 112 | K4: 0 | L4: 精准远程，暴击成长明显但攻速保守。
A5: Weapon_FireWand | B5: 火焰法杖 | C5: 强力武器 | D5: 成长 | E5: 魔法 | F5: 魔法范围持续输出 | G5: 3+ | H5: 45 | I5: 38 | J5: 152 | K5: 0 | L5: 强力武器，范围和魔法收益潜力高。成长标签暂按魔法构筑承载处理。
A6: Weapon_SummonOrb | B6: 召唤法球 | C6: 强力武器 | D6: 成长 | E6: 召唤 | F6: 召唤持续输出 | G6: 4+ | H6: 35 | I6: 40 | J6: 160 | K6: 0 | L6: 召唤构筑入口，基础较慢但收益率高。
A7: Weapon_DaggerRing | B7: 匕首环 | C7: 正常武器 | D7: 快速 | E7: 近战/精准 | F7: 近身高频暴击 | G7: 2+ | H7: 65 | I7: 24 | J7: 96 | K7: 0 | L7: 近战快速精准混合，范围短，安全性低。
A8: Weapon_ArcaneBolt | B8: 奥术弹 | C8: 正常武器 | D8: 精准 | E8: 魔法 | F8: 魔法单体弹体 | G8: 1+ | H8: 70 | I8: 26 | J8: 104 | K8: 0 | L8: 魔法精准单体，介于猎枪和法杖之间。
A9: Weapon_GreatAxe | B9: 巨斧 | C9: 强力武器 | D9: 重型 | E9: 近战 | F9: 大范围低频近战 | G9: 5+ | H9: 35 | I9: 42 | J9: 168 | K9: 0 | L9: 强力重型，范围和单次伤害高，攻速短板明显。

Sheet 05_武器等级
A1: 武器ID | B1: 等级 | C1: Attack | D1: AttackSpeed | E1: CriticalChance | F1: CriticalPercent | G1: Range | H1: Knockback | I1: MeleeUsage | J1: RangedUsage | K1: MagicUsage | L1: SummonUsage | M1: 收益率 | N1: 持有者属性 | O1: 单体DPS | P1: 群体修正 | Q1: 机制修正 | R1: 安全修正 | S1: 等效DPS | T1: 等级价值倍率 | U1: 等级价格 | V1: 价格偏差 | W1: 备注
A2: Weapon_IronHammer | B2: 1 | C2: 36 | D2: 55 | E2: 0 | F2: 160 | G2: 150 | H2: 18 | I2: 80 | J2: 0 | K2: 0 | L2: 0 | M2: AS 60; CritChance 60; CritPercent 70; Range 80; Knockback 70; Melee 80 | N2: - | O2: =C2*(D2/100)*(1+E2/100*MAX(0,F2/100-1)) -> 19.8 | P2: 1 | Q2: 1 | R2: 1 | S2: =O2*P2*Q2*R2 -> 19.8 | T2: 1 | U2: =ROUND(VLOOKUP(A2,'04_武器主表'!$A:$I,9,FALSE)*T2,0) -> 25 | V2: =U2-ROUND(VLOOKUP(A2,'04_武器主表'!$A:$J,10,FALSE)/4*T2,0) -> 0 | W2: Lv1 重击入口。
A3: Weapon_IronHammer | B3: 2 | C3: 52 | D3: 58 | E3: 0 | F3: 165 | G3: 165 | H3: 22 | I3: 90 | J3: 0 | K3: 0 | L3: 0 | M3: AS 60; CritChance 60; CritPercent 75; Range 85; Knockback 75; Melee 90 | N3: - | O3: =C3*(D3/100)*(1+E3/100*MAX(0,F3/100-1)) -> 30.16 | P3: 1.06 | Q3: 1 | R3: 1.02 | S3: =O3*P3*Q3*R3 -> 32.608992 | T3: 1.6 | U3: =ROUND(VLOOKUP(A3,'04_武器主表'!$A:$I,9,FALSE)*T3,0) -> 40 | V3: =U3-ROUND(VLOOKUP(A3,'04_武器主表'!$A:$J,10,FALSE)/4*T3,0) -> 0 | W3: 提高基础攻击和范围。
A4: Weapon_IronHammer | B4: 3 | C4: 72 | D4: 62 | E4: 2 | F4: 170 | G4: 180 | H4: 26 | I4: 100 | J4: 0 | K4: 0 | L4: 0 | M4: AS 65; CritChance 65; CritPercent 80; Range 90; Knockback 80; Melee 100 | N4: - | O4: =C4*(D4/100)*(1+E4/100*MAX(0,F4/100-1)) -> 45.26496 | P4: 1.12 | Q4: 1 | R4: 1.03 | S4: =O4*P4*Q4*R4 -> 52.217658 | T4: 3.6 | U4: =ROUND(VLOOKUP(A4,'04_武器主表'!$A:$I,9,FALSE)*T4,0) -> 90 | V4: =U4-ROUND(VLOOKUP(A4,'04_武器主表'!$A:$J,10,FALSE)/4*T4,0) -> 0 | W4: 中段成型，少量暴击。
A5: Weapon_IronHammer | B5: 4 | C5: 102 | D5: 66 | E5: 4 | F5: 180 | G5: 205 | H5: 32 | I5: 110 | J5: 0 | K5: 0 | L5: 0 | M5: AS 65; CritChance 70; CritPercent 85; Range 95; Knockback 85; Melee 110 | N5: - | O5: =C5*(D5/100)*(1+E5/100*MAX(0,F5/100-1)) -> 69.47424 | P5: 1.2 | Q5: 1 | R5: 1.05 | S5: =O5*P5*Q5*R5 -> 87.537542 | T5: 7.2 | U5: =ROUND(VLOOKUP(A5,'04_武器主表'!$A:$I,9,FALSE)*T5,0) -> 180 | V5: =U5-ROUND(VLOOKUP(A5,'04_武器主表'!$A:$J,10,FALSE)/4*T5,0) -> 0 | W5: 完整重型形态。
A6: Weapon_RapidSMG | B6: 1 | C6: 9 | D6: 210 | E6: 2 | F6: 150 | G6: 650 | H6: 2 | I6: 0 | J6: 100 | K6: 0 | L6: 0 | M6: AS 80; CritChance 40; CritPercent 40; Range 70; Knockback 25; Ranged 70 | N6: - | O6: =C6*(D6/100)*(1+E6/100*MAX(0,F6/100-1)) -> 19.089 | P6: 1 | Q6: 1 | R6: 1 | S6: =O6*P6*Q6*R6 -> 19.089 | T6: 1 | U6: =ROUND(VLOOKUP(A6,'04_武器主表'!$A:$I,9,FALSE)*T6,0) -> 25 | V6: =U6-ROUND(VLOOKUP(A6,'04_武器主表'!$A:$J,10,FALSE)/4*T6,0) -> 0 | W6: 高频基础入口。
A7: Weapon_RapidSMG | B7: 2 | C7: 11 | D7: 250 | E7: 2 | F7: 150 | G7: 680 | H7: 2 | I7: 0 | J7: 110 | K7: 0 | L7: 0 | M7: AS 82; CritChance 40; CritPercent 40; Range 75; Knockback 25; Ranged 80 | N7: - | O7: =C7*(D7/100)*(1+E7/100*MAX(0,F7/100-1)) -> 27.775 | P7: 1.1 | Q7: 1 | R7: 1 | S7: =O7*P7*Q7*R7 -> 30.5525 | T7: 1.6 | U7: =ROUND(VLOOKUP(A7,'04_武器主表'!$A:$I,9,FALSE)*T7,0) -> 40 | V7: =U7-ROUND(VLOOKUP(A7,'04_武器主表'!$A:$J,10,FALSE)/4*T7,0) -> 0 | W7: 主加攻速。
A8: Weapon_RapidSMG | B8: 3 | C8: 14 | D8: 295 | E8: 3 | F8: 155 | G8: 710 | H8: 3 | I8: 0 | J8: 120 | K8: 0 | L8: 0 | M8: AS 84; CritChance 45; CritPercent 45; Range 80; Knockback 30; Ranged 90 | N8: - | O8: =C8*(D8/100)*(1+E8/100*MAX(0,F8/100-1)) -> 41.98145 | P8: 1.18 | Q8: 1 | R8: 1 | S8: =O8*P8*Q8*R8 -> 49.538111 | T8: 3.6 | U8: =ROUND(VLOOKUP(A8,'04_武器主表'!$A:$I,9,FALSE)*T8,0) -> 90 | V8: =U8-ROUND(VLOOKUP(A8,'04_武器主表'!$A:$J,10,FALSE)/4*T8,0) -> 0 | W8: 提高单发和攻速。
A9: Weapon_RapidSMG | B9: 4 | C9: 18 | D9: 350 | E9: 4 | F9: 160 | G9: 750 | H9: 3 | I9: 0 | J9: 135 | K9: 0 | L9: 0 | M9: AS 85; CritChance 45; CritPercent 45; Range 85; Knockback 30; Ranged 100 | N9: - | O9: =C9*(D9/100)*(1+E9/100*MAX(0,F9/100-1)) -> 64.512 | P9: 1.25 | Q9: 1 | R9: 1 | S9: =O9*P9*Q9*R9 -> 80.64 | T9: 7.2 | U9: =ROUND(VLOOKUP(A9,'04_武器主表'!$A:$I,9,FALSE)*T9,0) -> 180 | V9: =U9-ROUND(VLOOKUP(A9,'04_武器主表'!$A:$J,10,FALSE)/4*T9,0) -> 0 | W9: 完整快速形态。
A10: Weapon_HuntingRifle | B10: 1 | C10: 28 | D10: 80 | E10: 10 | F10: 180 | G10: 850 | H10: 6 | I10: 0 | J10: 100 | K10: 0 | L10: 0 | M10: AS 70; CritChance 80; CritPercent 90; Range 90; Knockback 55; Ranged 85 | N10: - | O10: =C10*(D10/100)*(1+E10/100*MAX(0,F10/100-1)) -> 24.192 | P10: 1 | Q10: 1 | R10: 1 | S10: =O10*P10*Q10*R10 -> 24.192 | T10: 1 | U10: =ROUND(VLOOKUP(A10,'04_武器主表'!$A:$I,9,FALSE)*T10,0) -> 28 | V10: =U10-ROUND(VLOOKUP(A10,'04_武器主表'!$A:$J,10,FALSE)/4*T10,0) -> 0 | W10: 精准入门。
A11: Weapon_HuntingRifle | B11: 2 | C11: 38 | D11: 84 | E11: 14 | F11: 190 | G11: 900 | H11: 7 | I11: 0 | J11: 110 | K11: 0 | L11: 0 | M11: AS 70; CritChance 85; CritPercent 95; Range 95; Knockback 60; Ranged 95 | N11: - | O11: =C11*(D11/100)*(1+E11/100*MAX(0,F11/100-1)) -> 35.94192 | P11: 1.06 | Q11: 1 | R11: 1.02 | S11: =O11*P11*Q11*R11 -> 38.860404 | T11: 1.6 | U11: =ROUND(VLOOKUP(A11,'04_武器主表'!$A:$I,9,FALSE)*T11,0) -> 45 | V11: =U11-ROUND(VLOOKUP(A11,'04_武器主表'!$A:$J,10,FALSE)/4*T11,0) -> 0 | W11: 提高暴击和攻击。
A12: Weapon_HuntingRifle | B12: 3 | C12: 52 | D12: 88 | E12: 18 | F12: 205 | G12: 950 | H12: 8 | I12: 0 | J12: 120 | K12: 0 | L12: 0 | M12: AS 75; CritChance 90; CritPercent 100; Range 100; Knockback 65; Ranged 105 | N12: - | O12: =C12*(D12/100)*(1+E12/100*MAX(0,F12/100-1)) -> 54.40864 | P12: 1.12 | Q12: 1 | R12: 1.03 | S12: =O12*P12*Q12*R12 -> 62.765807 | T12: 3.6 | U12: =ROUND(VLOOKUP(A12,'04_武器主表'!$A:$I,9,FALSE)*T12,0) -> 101 | V12: =U12-ROUND(VLOOKUP(A12,'04_武器主表'!$A:$J,10,FALSE)/4*T12,0) -> 0 | W12: 暴击成型。
A13: Weapon_HuntingRifle | B13: 4 | C13: 70 | D13: 94 | E13: 24 | F13: 225 | G13: 1020 | H13: 9 | I13: 0 | J13: 135 | K13: 0 | L13: 0 | M13: AS 75; CritChance 95; CritPercent 110; Range 105; Knockback 70; Ranged 120 | N13: - | O13: =C13*(D13/100)*(1+E13/100*MAX(0,F13/100-1)) -> 85.54 | P13: 1.18 | Q13: 1 | R13: 1.04 | S13: =O13*P13*Q13*R13 -> 104.97469 | T13: 7.2 | U13: =ROUND(VLOOKUP(A13,'04_武器主表'!$A:$I,9,FALSE)*T13,0) -> 202 | V13: =U13-ROUND(VLOOKUP(A13,'04_武器主表'!$A:$J,10,FALSE)/4*T13,0) -> 0 | W13: 后期精准核心。
... A33: Weapon_GreatAxe | B33: 4 | C33: 160 | D33: 56 | E33: 5 | F33: 200 | G33: 270 | H33: 52 | I33: 170 | J33: 0 | K33: 0 | L33: 0 | M33: AS 58; CritChance 70; CritPercent 95; Range 100; Knockback 95; Melee 155 | N33: - | O33: =C33*(D33/100)*(1+E33/100*MAX(0,F33/100-1)) -> 94.08 | P33: 1.65 | Q33: 1 | R33: 1.15 | S33: =O33*P33*Q33*R33 -> 178.5168 | T33: 7.2 | U33: =ROUND(VLOOKUP(A33,'04_武器主表'!$A:$I,9,FALSE)*T33,0) -> 302 | V33: =U33-ROUND(VLOOKUP(A33,'04_武器主表'!$A:$J,10,FALSE)/4*T33,0) -> 0 | W33: 完整高成本重型。

Sheet 06_怪物主表
A1: 怪物ID | B1: 名称 | C1: 定位 | D1: MaxHealth | E1: Attack | F1: AttackSpeed | G1: MoveSpeed | H1: DetectionRange | I1: AttackRange | J1: Armor | K1: KnockbackResistance | L1: 行为参数 | M1: 奖励基准 | N1: 默认标签 | O1: 命中可靠性 | P1: 预期接触率 | Q1: 单体生存压力 | R1: 单体伤害压力 | S1: 备注
A2: SkeletonEnemy | B2: 骷髅 | C2: 标准近战小怪 | D2: 32 | E2: 15 | F2: 72 | G2: 380 | H2: 180 | I2: 165 | J2: 0 | K2: 0 | L2: SkeletonEnemySO；骷髅类近战使用 AttackRange 半圆做入场检测和提交命中覆盖；DetectionRange 仅保留近战量级，不按感知距离放大；结构来自现有资产，面板为设计版 | M2: 经验1；掉落18%；普通奖励池 | N2: Normal | O2: 0.35 | P2: 0.25 | Q2: =D2 -> 32 | R2: =ROUND(E2*(F2/100)*O2,2) -> 3.78 | S2: 1波基准普通近战，大部分1级武器应能一击或接近一击击杀。DetectionRange 不决定追击。
A3: EvilSlimeEnemy | B3: 邪恶史莱姆 | C3: 快速近战小怪 | D3: 24 | E3: 10 | F3: 100 | G3: 540 | H3: 150 | I3: 135 | J3: 0 | K3: 0 | L3: SkeletonEnemySO；骷髅类近战使用 AttackRange 半圆做入场检测和提交命中覆盖；DetectionRange 仅保留近战量级，不按感知距离放大；结构来自现有资产，面板为设计版 | M3: 经验1；掉落12%；普通奖励池 | N3: Normal;Fast | O3: 0.5 | P3: 0.4 | Q3: =D3 -> 24 | R3: =ROUND(E3*(F3/100)*O3,2) -> 5 | S3: 前期速度压力单位，低血低伤，用接触率制造风险。DetectionRange 不决定追击。
A4: WormEnemy | B4: 蠕虫 | C4: 低频远程风筝怪 | D4: 32 | E4: 12 | F4: 36 | G4: 270 | H4: 900 | I4: 760 | J4: 0 | K4: 0 | L4: WormEnemySO；远程投射物用 DetectionRange 做攻击释放入场，AttackRange 决定投射物最大飞行距离；后撤距离按检测范围比例配置；结构来自现有资产，面板为设计版 | M4: 经验1；掉落18%；普通奖励池 | N4: Ranged | O4: 0.36 | P4: 0.3 | Q4: =D4 -> 32 | R4: =ROUND(E4*(F4/100)*O4,2) -> 1.56 | S4: 远程骚扰，会后撤，主要考验追击与走位。DetectionRange 只代表可开始攻击的距离。
A5: FlyForestEnemy | B5: 森林飞虫 | C5: 标准远程风筝怪 | D5: 30 | E5: 11 | F5: 48 | G5: 320 | H5: 900 | I5: 820 | J5: 0 | K5: 0 | L5: FlyForestEnemySO；绕圈风筝；DetectionRange 做射击释放入场，AttackRange 决定投射物最大飞行距离；结构来自现有资产，面板为设计版 | M5: 经验1；掉落18%；普通奖励池 | N5: Ranged | O5: 0.4 | P5: 0.35 | Q5: =D5 -> 30 | R5: =ROUND(E5*(F5/100)*O5,2) -> 2.11 | S5: 常规远程怪模板，可比 Worm 更稳定进入池。DetectionRange 不是发现/追击距离。
A6: EvilEyeEnemy | B6: 邪眼 | C6: 脆皮高威胁远程 | D6: 22 | E6: 16 | F6: 42 | G6: 300 | H6: 920 | I6: 780 | J6: 0 | K6: 0 | L6: WormEnemySO；远程投射物用 DetectionRange 做攻击释放入场，AttackRange 决定投射物最大飞行距离；后撤风筝；结构来自现有资产，面板为设计版 | M6: 经验1；掉落18%；普通奖励池 | N6: Ranged;Special | O6: 0.42 | P6: 0.34 | Q6: =D6 -> 22 | R6: =ROUND(E6*(F6/100)*O6,2) -> 2.82 | S6: 低血高威胁远程，少量投放，不作为密度主体。DetectionRange 只代表可开始攻击的距离。
A7: SkeletonMeteorhammerEnemy | B7: 骷髅流星锤 | C7: 中距离重型近战 | D7: 70 | E7: 20 | F7: 60 | G7: 340 | H7: 250 | I7: 230 | J7: 0 | K7: 8 | L7: SkeletonMeteorhammerEnemySO；骷髅类近战使用 AttackRange 半圆做入场检测；两段提交分别用 AttackRange 倍率计算覆盖；DetectionRange 仅略高于基础覆盖；结构来自现有资产，面板为设计版 | M7: 经验2；掉落30%；重型奖励池 | N7: Heavy;Special | O7: 0.38 | P7: 0.26 | Q7: =D7 -> 70 | R7: =ROUND(E7*(F7/100)*O7,2) -> 4.56 | S7: 重型/特殊近战，一型负责中距离扫击压力。DetectionRange 不决定追击。
A8: SkeletonMeteorhammer2Enemy | B8: 骷髅流星锤二型 | C8: 长条扫击特殊近战 | D8: 68 | E8: 18 | F8: 58 | G8: 340 | H8: 250 | I8: 230 | J8: 0 | K8: 8 | L8: SkeletonMeteorhammer2EnemySO；第一段用 AttackRange 半圆，第二段用 AttackRange 计算前方矩形长度；DetectionRange 仅略高于基础覆盖；结构来自现有资产，面板为设计版 | M8: 经验2；掉落32%；重型奖励池 | N8: Heavy;Special | O8: 0.42 | P8: 0.3 | Q8: =D8 -> 68 | R8: =ROUND(E8*(F8/100)*O8,2) -> 4.38 | S8: 一型的后期替代/升级生态位，攻击覆盖形态更危险，基础伤害略保守。DetectionRange 不决定追击。
A9: BlueGolemEnemy | B9: 蓝石头人 | C9: 冲锋重型怪 | D9: 110 | E9: 26 | F9: 42 | G9: 250 | H9: 260 | I9: 220 | J9: 2 | K9: 40 | L9: GolemEnemySO；重型普攻用 DetectionRange 做攻击释放入场，提交后用 AttackRange 做近战圆形覆盖；DetectionRange 只略高于普攻覆盖，避免过早挥空；冲锋为独立行为；结构来自现有资产，面板为设计版 | M9: 经验2；掉落35%；重型奖励池 | N9: Heavy;Special | O9: 0.4 | P9: 0.28 | Q9: =D9 -> 110 | R9: =ROUND(E9*(F9/100)*O9,2) -> 4.37 | S9: 高生命、高抗击退、冲锋破站位。DetectionRange 只代表可开始普攻的距离。
A10: OrangeGolemEnemy | B10: 橙石头人 | C10: 高压重型/准精英 | D10: 150 | E10: 34 | F10: 38 | G10: 230 | H10: 280 | I10: 235 | J10: 4 | K10: 55 | L10: GolemEnemySO；高压重型普攻用 DetectionRange 做攻击释放入场，提交后用 AttackRange 做近战圆形覆盖；DetectionRange 只略高于普攻覆盖，避免过早挥空；冲锋为独立行为；结构来自现有资产，面板为设计版 | M10: 经验4；掉落100%；精英奖励池 | N10: Elite;Heavy | O10: 0.52 | P10: 0.4 | Q10: =D10 -> 150 | R10: =ROUND(E10*(F10/100)*O10,2) -> 6.72 | S10: 后期低频高压单位，承担准精英压力。DetectionRange 只代表可开始普攻的距离。
A11: MechaStoneBossEnemy | B11: 机械石像Boss | C11: Boss | D11: 3500 | E11: 42 | F11: 35 | G11: 200 | H11: 420 | I11: 320 | J11: 6 | K11: 100 | L11: GolemMechaStoneBossSO；近战用 MeleeRangeMultiplier 同时放大入场和近战覆盖；射击用 ShootRangeMultiplier 同时放大入场和投射物最大飞行距离；激光用 LaserLength/技能参数控制实际覆盖；结构来自现有资产，面板为设计版 | M11: 经验12；固定Boss奖励 | N11: BossLike | O11: 0.58 | P11: 0.5 | Q11: =D11 -> 3500 | R11: =ROUND(E11*(F11/100)*O11,2) -> 8.53 | S11: 节点Boss，多阶段远近混合压力。远程射击必须让倍率吃到投射物最大距离，否则会远处开火但弹体过早消失。

Sheet 07_怪物波次池
A1: 怪物ID | B1: 波次段 | C1: 权重 | D1: 数量占比 | E1: 额外压力标签 | F1: 生成位置 | G1: 奖励修正 | H1: 关键波次面板 | I1: 目标击杀时间 | J1: 压力贡献 | K1: 备注
A2: SkeletonEnemy | B2: 1-4 | C2: 70 | D2: 0.7 | E2: Normal | F2: 地图边缘持续生成 | G2: 默认 | H2: ="W1 HP "&ROUND(VLOOKUP($A2,'06_怪物主表'!$A:$S,4,FALSE)*1*(IF(ISNUMBER(SEARCH("BossLike",$E2)),1.45,1)*IF(ISNUMBER(SEARCH("Boss;",$E2&";")),1.6,1)*IF(ISNUMBER(SEARCH("Elite",$E2)),1.3,1)),0)&" / Atk "&ROUND(VLOOKUP($A2,'06_怪物主表'!$A:$S,5,FALSE)*1*(IF(ISNUMBER(SEARCH("BossLike",$E2)),1.18,1)*IF(ISNUMBER(SEARCH("Boss;",$E2&";")),1.25,1)*IF(ISNUMBER(SEARCH("Elite",$E2)),1.18,1)*IF(ISNUMBER(SEARCH("Ranged",$E2)),1.05,1)),0)&" / AS "&ROUND(VLOOKUP($A2,'06_怪物主表'!$A:$S,6,FALSE)*1,0) -> W1 HP 32 / Atk 15 / AS 72 | I2: 0.8-1.5秒 | J2: =IF(ISNUMBER($D2),ROUND(VLOOKUP($A2,'06_怪物主表'!$A:$S,18,FALSE)*$D2*VLOOKUP($A2,'06_怪物主表'!$A:$S,16,FALSE)*1*1*(IF(ISNUMBER(SEARCH("BossLike",$E2)),1.18,1)*IF(ISNUMBER(SEARCH("Boss;",$E2&";")),1.25,1)*IF(ISNUMBER(SEARCH("Elite",$E2)),1.18,1)*IF(ISNUMBER(SEARCH("Ranged",$E2)),1.05,1)),2),"节点固定") -> 0.66 | K2: 前期普通近战基准。
A3: EvilSlimeEnemy | B3: 1-4 | C3: 30 | D3: 0.3 | E3: Fast | F3: 边缘侧翼少量夹击 | G3: 快速怪掉率 | H3: ="W1 HP "&ROUND(VLOOKUP($A3,'06_怪物主表'!$A:$S,4,FALSE)*1*(IF(ISNUMBER(SEARCH("BossLike",$E3)),1.45,1)*IF(ISNUMBER(SEARCH("Boss;",$E3&";")),1.6,1)*IF(ISNUMBER(SEARCH("Elite",$E3)),1.3,1)),0)&" / Atk "&ROUND(VLOOKUP($A3,'06_怪物主表'!$A:$S,5,FALSE)*1*(IF(ISNUMBER(SEARCH("BossLike",$E3)),1.18,1)*IF(ISNUMBER(SEARCH("Boss;",$E3&";")),1.25,1)*IF(ISNUMBER(SEARCH("Elite",$E3)),1.18,1)*IF(ISNUMBER(SEARCH("Ranged",$E3)),1.05,1)),0)&" / AS "&ROUND(VLOOKUP($A3,'06_怪物主表'!$A:$S,6,FALSE)*1,0) -> W1 HP 24 / Atk 10 / AS 100 | I3: 0.5-1.0秒 | J3: =IF(ISNUMBER($D3),ROUND(VLOOKUP($A3,'06_怪物主表'!$A:$S,18,FALSE)*$D3*VLOOKUP($A3,'06_怪物主表'!$A:$S,16,FALSE)*1*1*(IF(ISNUMBER(SEARCH("BossLike",$E3)),1.18,1)*IF(ISNUMBER(SEARCH("Boss;",$E3&";")),1.25,1)*IF(ISNUMBER(SEARCH("Elite",$E3)),1.18,1)*IF(ISNUMBER(SEARCH("Ranged",$E3)),1.05,1)),2),"节点固定") -> 0.6 | K3: 开局只提供少量速度压力。
A4: SkeletonEnemy | B4: 5-9 | C4: 35 | D4: 0.35 | E4: Normal | F4: 地图边缘持续生成 | G4: 默认 | H4: ="W5 HP "&ROUND(VLOOKUP($A4,'06_怪物主表'!$A:$S,4,FALSE)*1.35*(IF(ISNUMBER(SEARCH("BossLike",$E4)),1.45,1)*IF(ISNUMBER(SEARCH("Boss;",$E4&";")),1.6,1)*IF(ISNUMBER(SEARCH("Elite",$E4)),1.3,1)),0)&" / Atk "&ROUND(VLOOKUP($A4,'06_怪物主表'!$A:$S,5,FALSE)*1.1*(IF(ISNUMBER(SEARCH("BossLike",$E4)),1.18,1)*IF(ISNUMBER(SEARCH("Boss;",$E4&";")),1.25,1)*IF(ISNUMBER(SEARCH("Elite",$E4)),1.18,1)*IF(ISNUMBER(SEARCH("Ranged",$E4)),1.05,1)),0)&" / AS "&ROUND(VLOOKUP($A4,'06_怪物主表'!$A:$S,6,FALSE)*1,0) -> W5 HP 43 / Atk 17 / AS 72 | I4: 0.7-1.3秒 | J4: =IF(ISNUMBER($D4),ROUND(VLOOKUP($A4,'06_怪物主表'!$A:$S,18,FALSE)*$D4*VLOOKUP($A4,'06_怪物主表'!$A:$S,16,FALSE)*1.1*1*(IF(ISNUMBER(SEARCH("BossLike",$E4)),1.18,1)*IF(ISNUMBER(SEARCH("Boss;",$E4&";")),1.25,1)*IF(ISNUMBER(SEARCH("Elite",$E4)),1.18,1)*IF(ISNUMBER(SEARCH("Ranged",$E4)),1.05,1)),2),"节点固定") -> 0.36 | K4: 维持基础清场节奏。
A5: EvilSlimeEnemy | B5: 5-9 | C5: 25 | D5: 0.25 | E5: Fast | F5: 侧翼夹击 | G5: 快速怪掉率 | H5: ="W5 HP "&ROUND(VLOOKUP($A5,'06_怪物主表'!$A:$S,4,FALSE)*1.35*(IF(ISNUMBER(SEARCH("BossLike",$E5)),1.45,1)*IF(ISNUMBER(SEARCH("Boss;",$E5&";")),1.6,1)*IF(ISNUMBER(SEARCH("Elite",$E5)),1.3,1)),0)&" / Atk "&ROUND(VLOOKUP($A5,'06_怪物主表'!$A:$S,5,FALSE)*1.1*(IF(ISNUMBER(SEARCH("BossLike",$E5)),1.18,1)*IF(ISNUMBER(SEARCH("Boss;",$E5&";")),1.25,1)*IF(ISNUMBER(SEARCH("Elite",$E5)),1.18,1)*IF(ISNUMBER(SEARCH("Ranged",$E5)),1.05,1)),0)&" / AS "&ROUND(VLOOKUP($A5,'06_怪物主表'!$A:$S,6,FALSE)*1,0) -> W5 HP 32 / Atk 11 / AS 100 | I5: 0.5-0.9秒 | J5: =IF(ISNUMBER($D5),ROUND(VLOOKUP($A5,'06_怪物主表'!$A:$S,18,FALSE)*$D5*VLOOKUP($A5,'06_怪物主表'!$A:$S,16,FALSE)*1.1*1*(IF(ISNUMBER(SEARCH("BossLike",$E5)),1.18,1)*IF(ISNUMBER(SEARCH("Boss;",$E5&";")),1.25,1)*IF(ISNUMBER(SEARCH("Elite",$E5)),1.18,1)*IF(ISNUMBER(SEARCH("Ranged",$E5)),1.05,1)),2),"节点固定") -> 0.55 | K5: 制造漏怪惩罚。
A6: WormEnemy | B6: 5-9 | C6: 13 | D6: 0.13 | E6: Ranged | F6: 边缘远程点，保留预警距离 | G6: 默认 | H6: ="W5 HP "&ROUND(VLOOKUP($A6,'06_怪物主表'!$A:$S,4,FALSE)*1.35*(IF(ISNUMBER(SEARCH("BossLike",$E6)),1.45,1)*IF(ISNUMBER(SEARCH("Boss;",$E6&";")),1.6,1)*IF(ISNUMBER(SEARCH("Elite",$E6)),1.3,1)),0)&" / Atk "&ROUND(VLOOKUP($A6,'06_怪物主表'!$A:$S,5,FALSE)*1.1*(IF(ISNUMBER(SEARCH("BossLike",$E6)),1.18,1)*IF(ISNUMBER(SEARCH("Boss;",$E6&";")),1.25,1)*IF(ISNUMBER(SEARCH("Elite",$E6)),1.18,1)*IF(ISNUMBER(SEARCH("Ranged",$E6)),1.05,1)),0)&" / AS "&ROUND(VLOOKUP($A6,'06_怪物主表'!$A:$S,6,FALSE)*1,0) -> W5 HP 43 / Atk 14 / AS 36 | I6: 0.8-1.4秒 | J6: =IF(ISNUMBER($D6),ROUND(VLOOKUP($A6,'06_怪物主表'!$A:$S,18,FALSE)*$D6*VLOOKUP($A6,'06_怪物主表'!$A:$S,16,FALSE)*1.1*1*(IF(ISNUMBER(SEARCH("BossLike",$E6)),1.18,1)*IF(ISNUMBER(SEARCH("Boss;",$E6&";")),1.25,1)*IF(ISNUMBER(SEARCH("Elite",$E6)),1.18,1)*IF(ISNUMBER(SEARCH("Ranged",$E6)),1.05,1)),2),"节点固定") -> 0.07 | K6: 低频远程骚扰。 DetectionRange 控制攻击释放入场，AttackRange 控制投射物最大距离。
A7: FlyForestEnemy | B7: 5-9 | C7: 10 | D7: 0.1 | E7: Ranged | F7: 边缘远程点 | G7: 默认 | H7: ="W5 HP "&ROUND(VLOOKUP($A7,'06_怪物主表'!$A:$S,4,FALSE)*1.35*(IF(ISNUMBER(SEARCH("BossLike",$E7)),1.45,1)*IF(ISNUMBER(SEARCH("Boss;",$E7&";")),1.6,1)*IF(ISNUMBER(SEARCH("Elite",$E7)),1.3,1)),0)&" / Atk "&ROUND(VLOOKUP($A7,'06_怪物主表'!$A:$S,5,FALSE)*1.1*(IF(ISNUMBER(SEARCH("BossLike",$E7)),1.18,1)*IF(ISNUMBER(SEARCH("Boss;",$E7&";")),1.25,1)*IF(ISNUMBER(SEARCH("Elite",$E7)),1.18,1)*IF(ISNUMBER(SEARCH("Ranged",$E7)),1.05,1)),0)&" / AS "&ROUND(VLOOKUP($A7,'06_怪物主表'!$A:$S,6,FALSE)*1,0) -> W5 HP 41 / Atk 13 / AS 48 | I7: 0.8-1.4秒 | J7: =IF(ISNUMBER($D7),ROUND(VLOOKUP($A7,'06_怪物主表'!$A:$S,18,FALSE)*$D7*VLOOKUP($A7,'06_怪物主表'!$A:$S,16,FALSE)*1.1*1*(IF(ISNUMBER(SEARCH("BossLike",$E7)),1.18,1)*IF(ISNUMBER(SEARCH("Boss;",$E7&";")),1.25,1)*IF(ISNUMBER(SEARCH("Elite",$E7)),1.18,1)*IF(ISNUMBER(SEARCH("Ranged",$E7)),1.05,1)),2),"节点固定") -> 0.09 | K7: 标准远程开始进入池。 DetectionRange 控制攻击释放入场，AttackRange 控制投射物最大距离。
A8: SkeletonMeteorhammerEnemy | B8: 5-9 | C8: 15 | D8: 0.15 | E8: Heavy;Special | F8: 边缘慢速推进 | G8: 经验2；重型奖励池 | H8: ="W5 HP "&ROUND(VLOOKUP($A8,'06_怪物主表'!$A:$S,4,FALSE)*1.35*(IF(ISNUMBER(SEARCH("BossLike",$E8)),1.45,1)*IF(ISNUMBER(SEARCH("Boss;",$E8&";")),1.6,1)*IF(ISNUMBER(SEARCH("Elite",$E8)),1.3,1)),0)&" / Atk "&ROUND(VLOOKUP($A8,'06_怪物主表'!$A:$S,5,FALSE)*1.1*(IF(ISNUMBER(SEARCH("BossLike",$E8)),1.18,1)*IF(ISNUMBER(SEARCH("Boss;",$E8&";")),1.25,1)*IF(ISNUMBER(SEARCH("Elite",$E8)),1.18,1)*IF(ISNUMBER(SEARCH("Ranged",$E8)),1.05,1)),0)&" / AS "&ROUND(VLOOKUP($A8,'06_怪物主表'!$A:$S,6,FALSE)*1,0) -> W5 HP 95 / Atk 22 / AS 60 | I8: 3.0-5.0秒 | J8: =IF(ISNUMBER($D8),ROUND(VLOOKUP($A8,'06_怪物主表'!$A:$S,18,FALSE)*$D8*VLOOKUP($A8,'06_怪物主表'!$A:$S,16,FALSE)*1.1*1*(IF(ISNUMBER(SEARCH("BossLike",$E8)),1.18,1)*IF(ISNUMBER(SEARCH("Boss;",$E8&";")),1.25,1)*IF(ISNUMBER(SEARCH("Elite",$E8)),1.18,1)*IF(ISNUMBER(SEARCH("Ranged",$E8)),1.05,1)),2),"节点固定") -> 0.2 | K8: 一型作为前中期重型近战。
A9: EvilEyeEnemy | B9: 5-9 | C9: 2 | D9: 0.02 | E9: Ranged;Special | F9: 远程预警点，低数量 | G9: 默认 | H9: ="W5 HP "&ROUND(VLOOKUP($A9,'06_怪物主表'!$A:$S,4,FALSE)*1.35*(IF(ISNUMBER(SEARCH("BossLike",$E9)),1.45,1)*IF(ISNUMBER(SEARCH("Boss;",$E9&";")),1.6,1)*IF(ISNUMBER(SEARCH("Elite",$E9)),1.3,1)),0)&" / Atk "&ROUND(VLOOKUP($A9,'06_怪物主表'!$A:$S,5,FALSE)*1.1*(IF(ISNUMBER(SEARCH("BossLike",$E9)),1.18,1)*IF(ISNUMBER(SEARCH("Boss;",$E9&";")),1.25,1)*IF(ISNUMBER(SEARCH("Elite",$E9)),1.18,1)*IF(ISNUMBER(SEARCH("Ranged",$E9)),1.05,1)),0)&" / AS "&ROUND(VLOOKUP($A9,'06_怪物主表'!$A:$S,6,FALSE)*1,0) -> W5 HP 30 / Atk 18 / AS 42 | I9: 0.7-1.3秒 | J9: =IF(ISNUMBER($D9),ROUND(VLOOKUP($A9,'06_怪物主表'!$A:$S,18,FALSE)*$D9*VLOOKUP($A9,'06_怪物主表'!$A:$S,16,FALSE)*1.1*1*(IF(ISNUMBER(SEARCH("BossLike",$E9)),1.18,1)*IF(ISNUMBER(SEARCH("Boss;",$E9&";")),1.25,1)*IF(ISNUMBER(SEARCH("Elite",$E9)),1.18,1)*IF(ISNUMBER(SEARCH("Ranged",$E9)),1.05,1)),2),"节点固定") -> 0.02 | K9: 只少量试投放，避免低血高伤远程过量。 DetectionRange 控制攻击释放入场，AttackRange 控制投射物最大距离。
A10: SkeletonEnemy | B10: 10-14 | C10: 24 | D10: 0.24 | E10: Normal | F10: 边缘持续生成 | G10: 默认 | H10: ="W10 HP "&ROUND(VLOOKUP($A10,'06_怪物主表'!$A:$S,4,FALSE)*2.2*(IF(ISNUMBER(SEARCH("BossLike",$E10)),1.45,1)*IF(ISNUMBER(SEARCH("Boss;",$E10&";")),1.6,1)*IF(ISNUMBER(SEARCH("Elite",$E10)),1.3,1)),0)&" / Atk "&ROUND(VLOOKUP($A10,'06_怪物主表'!$A:$S,5,FALSE)*1.32*(IF(ISNUMBER(SEARCH("BossLike",$E10)),1.18,1)*IF(ISNUMBER(SEARCH("Boss;",$E10&";")),1.25,1)*IF(ISNUMBER(SEARCH("Elite",$E10)),1.18,1)*IF(ISNUMBER(SEARCH("Ranged",$E10)),1.05,1)),0)&" / AS "&ROUND(VLOOKUP($A10,'06_怪物主表'!$A:$S,6,FALSE)*1.08,0) -> W10 HP 70 / Atk 20 / AS 78 | I10: 0.6-1.1秒 | J10: =IF(ISNUMBER($D10),ROUND(VLOOKUP($A10,'06_怪物主表'!$A:$S,18,FALSE)*$D10*VLOOKUP($A10,'06_怪物主表'!$A:$S,16,FALSE)*1.32*1.08*(IF(ISNUMBER(SEARCH("BossLike",$E10)),1.18,1)*IF(ISNUMBER(SEARCH("Boss;",$E10&";")),1.25,1)*IF(ISNUMBER(SEARCH("Elite",$E10)),1.18,1)*IF(ISNUMBER(SEARCH("Ranged",$E10)),1.05,1)),2),"节点固定") -> 0.32 | K10: 中期基础密度单位。
A11: EvilSlimeEnemy | B11: 10-14 | C11: 18 | D11: 0.18 | E11: Fast | F11: 侧翼/后方夹击 | G11: 快速怪掉率 | H11: ="W10 HP "&ROUND(VLOOKUP($A11,'06_怪物主表'!$A:$S,4,FALSE)*2.2*(IF(ISNUMBER(SEARCH("BossLike",$E11)),1.45,1)*IF(ISNUMBER(SEARCH("Boss;",$E11&";")),1.6,1)*IF(ISNUMBER(SEARCH("Elite",$E11)),1.3,1)),0)&" / Atk "&ROUND(VLOOKUP($A11,'06_怪物主表'!$A:$S,5,FALSE)*1.32*(IF(ISNUMBER(SEARCH("BossLike",$E11)),1.18,1)*IF(ISNUMBER(SEARCH("Boss;",$E11&";")),1.25,1)*IF(ISNUMBER(SEARCH("Elite",$E11)),1.18,1)*IF(ISNUMBER(SEARCH("Ranged",$E11)),1.05,1)),0)&" / AS "&ROUND(VLOOKUP($A11,'06_怪物主表'!$A:$S,6,FALSE)*1.08,0) -> W10 HP 53 / Atk 13 / AS 108 | I11: 0.4-0.8秒 | J11: =IF(ISNUMBER($D11),ROUND(VLOOKUP($A11,'06_怪物主表'!$A:$S,18,FALSE)*$D11*VLOOKUP($A11,'06_怪物主表'!$A:$S,16,FALSE)*1.32*1.08*(IF(ISNUMBER(SEARCH("BossLike",$E11)),1.18,1)*IF(ISNUMBER(SEARCH("Boss;",$E11&";")),1.25,1)*IF(ISNUMBER(SEARCH("Elite",$E11)),1.18,1)*IF(ISNUMBER(SEARCH("Ranged",$E11)),1.05,1)),2),"节点固定") -> 0.51 | K11: 峰值段占比受控。
A12: WormEnemy | B12: 10-14 | C12: 11 | D12: 0.11 | E12: Ranged | F12: 边缘远程点 | G12: 默认 | H12: ="W10 HP "&ROUND(VLOOKUP($A12,'06_怪物主表'!$A:$S,4,FALSE)*2.2*(IF(ISNUMBER(SEARCH("BossLike",$E12)),1.45,1)*IF(ISNUMBER(SEARCH("Boss;",$E12&";")),1.6,1)*IF(ISNUMBER(SEARCH("Elite",$E12)),1.3,1)),0)&" / Atk "&ROUND(VLOOKUP($A12,'06_怪物主表'!$A:$S,5,FALSE)*1.32*(IF(ISNUMBER(SEARCH("BossLike",$E12)),1.18,1)*IF(ISNUMBER(SEARCH("Boss;",$E12&";")),1.25,1)*IF(ISNUMBER(SEARCH("Elite",$E12)),1.18,1)*IF(ISNUMBER(SEARCH("Ranged",$E12)),1.05,1)),0)&" / AS "&ROUND(VLOOKUP($A12,'06_怪物主表'!$A:$S,6,FALSE)*1.08,0) -> W10 HP 70 / Atk 17 / AS 39 | I12: 0.7-1.2秒 | J12: =IF(ISNUMBER($D12),ROUND(VLOOKUP($A12,'06_怪物主表'!$A:$S,18,FALSE)*$D12*VLOOKUP($A12,'06_怪物主表'!$A:$S,16,FALSE)*1.32*1.08*(IF(ISNUMBER(SEARCH("BossLike",$E12)),1.18,1)*IF(ISNUMBER(SEARCH("Boss;",$E12&";")),1.25,1)*IF(ISNUMBER(SEARCH("Elite",$E12)),1.18,1)*IF(ISNUMBER(SEARCH("Ranged",$E12)),1.05,1)),2),"节点固定") -> 0.08 | K12: 风筝远程维持压力。 DetectionRange 控制攻击释放入场，AttackRange 控制投射物最大距离。
A13: FlyForestEnemy | B13: 10-14 | C13: 12 | D13: 0.12 | E13: Ranged | F13: 边缘远程点 | G13: 默认 | H13: ="W10 HP "&ROUND(VLOOKUP($A13,'06_怪物主表'!$A:$S,4,FALSE)*2.2*(IF(ISNUMBER(SEARCH("BossLike",$E13)),1.45,1)*IF(ISNUMBER(SEARCH("Boss;",$E13&";")),1.6,1)*IF(ISNUMBER(SEARCH("Elite",$E13)),1.3,1)),0)&" / Atk "&ROUND(VLOOKUP($A13,'06_怪物主表'!$A:$S,5,FALSE)*1.32*(IF(ISNUMBER(SEARCH("BossLike",$E13)),1.18,1)*IF(ISNUMBER(SEARCH("Boss;",$E13&";")),1.25,1)*IF(ISNUMBER(SEARCH("Elite",$E13)),1.18,1)*IF(ISNUMBER(SEARCH("Ranged",$E13)),1.05,1)),0)&" / AS "&ROUND(VLOOKUP($A13,'06_怪物主表'!$A:$S,6,FALSE)*1.08,0) -> W10 HP 66 / Atk 15 / AS 52 | I13: 0.7-1.2秒 | J13: =IF(ISNUMBER($D13),ROUND(VLOOKUP($A13,'06_怪物主表'!$A:$S,18,FALSE)*$D13*VLOOKUP($A13,'06_怪物主表'!$A:$S,16,FALSE)*1.32*1.08*(IF(ISNUMBER(SEARCH("BossLike",$E13)),1.18,1)*IF(ISNUMBER(SEARCH("Boss;",$E13&";")),1.25,1)*IF(ISNUMBER(SEARCH("Elite",$E13)),1.18,1)*IF(ISNUMBER(SEARCH("Ranged",$E13)),1.05,1)),2),"节点固定") -> 0.13 | K13: 标准远程常规化。 DetectionRange 控制攻击释放入场，AttackRange 控制投射物最大距离。
A14: EvilEyeEnemy | B14: 10-14 | C14: 6 | D14: 0.06 | E14: Ranged;Special | F14: 远程预警点 | G14: 默认 | H14: ="W10 HP "&ROUND(VLOOKUP($A14,'06_怪物主表'!$A:$S,4,FALSE)*2.2*(IF(ISNUMBER(SEARCH("BossLike",$E14)),1.45,1)*IF(ISNUMBER(SEARCH("Boss;",$E14&";")),1.6,1)*IF(ISNUMBER(SEARCH("Elite",$E14)),1.3,1)),0)&" / Atk "&ROUND(VLOOKUP($A14,'06_怪物主表'!$A:$S,5,FALSE)*1.32*(IF(ISNUMBER(SEARCH("BossLike",$E14)),1.18,1)*IF(ISNUMBER(SEARCH("Boss;",$E14&";")),1.25,1)*IF(ISNUMBER(SEARCH("Elite",$E14)),1.18,1)*IF(ISNUMBER(SEARCH("Ranged",$E14)),1.05,1)),0)&" / AS "&ROUND(VLOOKUP($A14,'06_怪物主表'!$A:$S,6,FALSE)*1.08,0) -> W10 HP 48 / Atk 22 / AS 45 | I14: 0.6-1.1秒 | J14: =IF(ISNUMBER($D14),ROUND(VLOOKUP($A14,'06_怪物主表'!$A:$S,18,FALSE)*$D14*VLOOKUP($A14,'06_怪物主表'!$A:$S,16,FALSE)*1.32*1.08*(IF(ISNUMBER(SEARCH("BossLike",$E14)),1.18,1)*IF(ISNUMBER(SEARCH("Boss;",$E14&";")),1.25,1)*IF(ISNUMBER(SEARCH("Elite",$E14)),1.18,1)*IF(ISNUMBER(SEARCH("Ranged",$E14)),1.05,1)),2),"节点固定") -> 0.09 | K14: 少量高威胁远程。 DetectionRange 控制攻击释放入场，AttackRange 控制投射物最大距离。
A15: SkeletonMeteorhammerEnemy | B15: 10-14 | C15: 14 | D15: 0.14 | E15: Heavy;Special | F15: 边缘慢速推进 | G15: 经验2；重型奖励池 | H15: ="W10 HP "&ROUND(VLOOKUP($A15,'06_怪物主表'!$A:$S,4,FALSE)*2.2*(IF(ISNUMBER(SEARCH("BossLike",$E15)),1.45,1)*IF(ISNUMBER(SEARCH("Boss;",$E15&";")),1.6,1)*IF(ISNUMBER(SEARCH("Elite",$E15)),1.3,1)),0)&" / Atk "&ROUND(VLOOKUP($A15,'06_怪物主表'!$A:$S,5,FALSE)*1.32*(IF(ISNUMBER(SEARCH("BossLike",$E15)),1.18,1)*IF(ISNUMBER(SEARCH("Boss;",$E15&";")),1.25,1)*IF(ISNUMBER(SEARCH("Elite",$E15)),1.18,1)*IF(ISNUMBER(SEARCH("Ranged",$E15)),1.05,1)),0)&" / AS "&ROUND(VLOOKUP($A15,'06_怪物主表'!$A:$S,6,FALSE)*1.08,0) -> W10 HP 154 / Atk 26 / AS 65 | I15: 3.5-5.5秒 | J15: =IF(ISNUMBER($D15),ROUND(VLOOKUP($A15,'06_怪物主表'!$A:$S,18,FALSE)*$D15*VLOOKUP($A15,'06_怪物主表'!$A:$S,16,FALSE)*1.32*1.08*(IF(ISNUMBER(SEARCH("BossLike",$E15)),1.18,1)*IF(ISNUMBER(SEARCH("Boss;",$E15&";")),1.25,1)*IF(ISNUMBER(SEARCH("Elite",$E15)),1.18,1)*IF(ISNUMBER(SEARCH("Ranged",$E15)),1.05,1)),2),"节点固定") -> 0.24 | K15: 中期主要重型近战。
A16: SkeletonMeteorhammer2Enemy | B16: 10-14 | C16: 9 | D16: 0.09 | E16: Heavy;Special | F16: 边缘慢速推进，峰值段少量 | G16: 经验2；重型奖励池 | H16: ="W10 HP "&ROUND(VLOOKUP($A16,'06_怪物主表'!$A:$S,4,FALSE)*2.2*(IF(ISNUMBER(SEARCH("BossLike",$E16)),1.45,1)*IF(ISNUMBER(SEARCH("Boss;",$E16&";")),1.6,1)*IF(ISNUMBER(SEARCH("Elite",$E16)),1.3,1)),0)&" / Atk "&ROUND(VLOOKUP($A16,'06_怪物主表'!$A:$S,5,FALSE)*1.32*(IF(ISNUMBER(SEARCH("BossLike",$E16)),1.18,1)*IF(ISNUMBER(SEARCH("Boss;",$E16&";")),1.25,1)*IF(ISNUMBER(SEARCH("Elite",$E16)),1.18,1)*IF(ISNUMBER(SEARCH("Ranged",$E16)),1.05,1)),0)&" / AS "&ROUND(VLOOKUP($A16,'06_怪物主表'!$A:$S,6,FALSE)*1.08,0) -> W10 HP 150 / Atk 24 / AS 63 | I16: 3.5-5.5秒 | J16: =IF(ISNUMBER($D16),ROUND(VLOOKUP($A16,'06_怪物主表'!$A:$S,18,FALSE)*$D16*VLOOKUP($A16,'06_怪物主表'!$A:$S,16,FALSE)*1.32*1.08*(IF(ISNUMBER(SEARCH("BossLike",$E16)),1.18,1)*IF(ISNUMBER(SEARCH("Boss;",$E16&";")),1.25,1)*IF(ISNUMBER(SEARCH("Elite",$E16)),1.18,1)*IF(ISNUMBER(SEARCH("Ranged",$E16)),1.05,1)),2),"节点固定") -> 0.17 | K16: 二型逐步替代一型部分权重。
A17: BlueGolemEnemy | B17: 10-14 | C17: 5 | D17: 0.05 | E17: Heavy;Special | F17: 节点/峰值段定点 | G17: 经验2；重型奖励池 | H17: ="W10 HP "&ROUND(VLOOKUP($A17,'06_怪物主表'!$A:$S,4,FALSE)*2.2*(IF(ISNUMBER(SEARCH("BossLike",$E17)),1.45,1)*IF(ISNUMBER(SEARCH("Boss;",$E17&";")),1.6,1)*IF(ISNUMBER(SEARCH("Elite",$E17)),1.3,1)),0)&" / Atk "&ROUND(VLOOKUP($A17,'06_怪物主表'!$A:$S,5,FALSE)*1.32*(IF(ISNUMBER(SEARCH("BossLike",$E17)),1.18,1)*IF(ISNUMBER(SEARCH("Boss;",$E17&";")),1.25,1)*IF(ISNUMBER(SEARCH("Elite",$E17)),1.18,1)*IF(ISNUMBER(SEARCH("Ranged",$E17)),1.05,1)),0)&" / AS "&ROUND(VLOOKUP($A17,'06_怪物主表'!$A:$S,6,FALSE)*1.08,0) -> W10 HP 242 / Atk 34 / AS 45 | I17: 3.5-6.0秒 | J17: =IF(ISNUMBER($D17),ROUND(VLOOKUP($A17,'06_怪物主表'!$A:$S,18,FALSE)*$D17*VLOOKUP($A17,'06_怪物主表'!$A:$S,16,FALSE)*1.32*1.08*(IF(ISNUMBER(SEARCH("BossLike",$E17)),1.18,1)*IF(ISNUMBER(SEARCH("Boss;",$E17&";")),1.25,1)*IF(ISNUMBER(SEARCH("Elite",$E17)),1.18,1)*IF(ISNUMBER(SEARCH("Ranged",$E17)),1.05,1)),2),"节点固定") -> 0.09 | K17: 冲锋重型低频进入。 DetectionRange 控制普攻入场，AttackRange 控制提交覆盖。
A18: MechaStoneBossEnemy | B18: 10-14 | C18: 0 | D18: 0.004 | E18: BossLike | F18: Boss入场点 | G18: 固定Boss奖励 | H18: ="W10 HP "&ROUND(VLOOKUP($A18,'06_怪物主表'!$A:$S,4,FALSE)*2.2*(IF(ISNUMBER(SEARCH("BossLike",$E18)),1.45,1)*IF(ISNUMBER(SEARCH("Boss;",$E18&";")),1.6,1)*IF(ISNUMBER(SEARCH("Elite",$E18)),1.3,1)),0)&" / Atk "&ROUND(VLOOKUP($A18,'06_怪物主表'!$A:$S,5,FALSE)*1.32*(IF(ISNUMBER(SEARCH("BossLike",$E18)),1.18,1)*IF(ISNUMBER(SEARCH("Boss;",$E18&";")),1.25,1)*IF(ISNUMBER(SEARCH("Elite",$E18)),1.18,1)*IF(ISNUMBER(SEARCH("Ranged",$E18)),1.05,1)),0)&" / AS "&ROUND(VLOOKUP($A18,'06_怪物主表'!$A:$S,6,FALSE)*1.08,0) -> W10 HP 11165 / Atk 65 / AS 38 | I18: 35-55秒 | J18: =IF(ISNUMBER($D18),ROUND(VLOOKUP($A18,'06_怪物主表'!$A:$S,18,FALSE)*$D18*VLOOKUP($A18,'06_怪物主表'!$A:$S,16,FALSE)*1.32*1.08*(IF(ISNUMBER(SEARCH("BossLike",$E18)),1.18,1)*IF(ISNUMBER(SEARCH("Boss;",$E18&";")),1.25,1)*IF(ISNUMBER(SEARCH("Elite",$E18)),1.18,1)*IF(ISNUMBER(SEARCH("Ranged",$E18)),1.05,1)),2),"节点固定") -> 0.03 | K18: Boss节点固定；射击倍率需同时覆盖释放距离和投射物最大飞行距离；激光范围走技能长度。
A19: SkeletonEnemy | B19: 15-19 | C19: 18 | D19: 0.18 | E19: Normal | F19: 边缘持续生成 | G19: 默认 | H19: ="W15 HP "&ROUND(VLOOKUP($A19,'06_怪物主表'!$A:$S,4,FALSE)*3.8*(IF(ISNUMBER(SEARCH("BossLike",$E19)),1.45,1)*IF(ISNUMBER(SEARCH("Boss;",$E19&";")),1.6,1)*IF(ISNUMBER(SEARCH("Elite",$E19)),1.3,1)),0)&" / Atk "&ROUND(VLOOKUP($A19,'06_怪物主表'!$A:$S,5,FALSE)*1.68*(IF(ISNUMBER(SEARCH("BossLike",$E19)),1.18,1)*IF(ISNUMBER(SEARCH("Boss;",$E19&";")),1.25,1)*IF(ISNUMBER(SEARCH("Elite",$E19)),1.18,1)*IF(ISNUMBER(SEARCH("Ranged",$E19)),1.05,1)),0)&" / AS "&ROUND(VLOOKUP($A19,'06_怪物主表'!$A:$S,6,FALSE)*1.16,0) -> W15 HP 122 / Atk 25 / AS 84 | I19: 0.5-1.0秒 | J19: =IF(ISNUMBER($D19),ROUND(VLOOKUP($A19,'06_怪物主表'!$A:$S,18,FALSE)*$D19*VLOOKUP($A19,'06_怪物主表'!$A:$S,16,FALSE)*1.68*1.16*(IF(ISNUMBER(SEARCH("BossLike",$E19)),1.18,1)*IF(ISNUMBER(SEARCH("Boss;",$E19&";")),1.25,1)*IF(ISNUMBER(SEARCH("Elite",$E19)),1.18,1)*IF(ISNUMBER(SEARCH("Ranged",$E19)),1.05,1)),2),"节点固定") -> 0.33 | K19: 后期基础数量压力。
A20: EvilSlimeEnemy | B20: 15-19 | C20: 14 | D20: 0.14 | E20: Fast | F20: 侧翼夹击 | G20: 快速怪掉率 | H20: ="W15 HP "&ROUND(VLOOKUP($A20,'06_怪物主表'!$A:$S,4,FALSE)*3.8*(IF(ISNUMBER(SEARCH("BossLike",$E20)),1.45,1)*IF(ISNUMBER(SEARCH("Boss;",$E20&";")),1.6,1)*IF(ISNUMBER(SEARCH("Elite",$E20)),1.3,1)),0)&" / Atk "&ROUND(VLOOKUP($A20,'06_怪物主表'!$A:$S,5,FALSE)*1.68*(IF(ISNUMBER(SEARCH("BossLike",$E20)),1.18,1)*IF(ISNUMBER(SEARCH("Boss;",$E20&";")),1.25,1)*IF(ISNUMBER(SEARCH("Elite",$E20)),1.18,1)*IF(ISNUMBER(SEARCH("Ranged",$E20)),1.05,1)),0)&" / AS "&ROUND(VLOOKUP($A20,'06_怪物主表'!$A:$S,6,FALSE)*1.16,0) -> W15 HP 91 / Atk 17 / AS 116 | I20: 0.35-0.75秒 | J20: =IF(ISNUMBER($D20),ROUND(VLOOKUP($A20,'06_怪物主表'!$A:$S,18,FALSE)*$D20*VLOOKUP($A20,'06_怪物主表'!$A:$S,16,FALSE)*1.68*1.16*(IF(ISNUMBER(SEARCH("BossLike",$E20)),1.18,1)*IF(ISNUMBER(SEARCH("Boss;",$E20&";")),1.25,1)*IF(ISNUMBER(SEARCH("Elite",$E20)),1.18,1)*IF(ISNUMBER(SEARCH("Ranged",$E20)),1.05,1)),2),"节点固定") -> 0.55 | K20: 快速压力控制在可读范围。
A21: WormEnemy | B21: 15-19 | C21: 8 | D21: 0.08 | E21: Ranged | F21: 边缘远程点 | G21: 默认 | H21: ="W15 HP "&ROUND(VLOOKUP($A21,'06_怪物主表'!$A:$S,4,FALSE)*3.8*(IF(ISNUMBER(SEARCH("BossLike",$E21)),1.45,1)*IF(ISNUMBER(SEARCH("Boss;",$E21&";")),1.6,1)*IF(ISNUMBER(SEARCH("Elite",$E21)),1.3,1)),0)&" / Atk "&ROUND(VLOOKUP($A21,'06_怪物主表'!$A:$S,5,FALSE)*1.68*(IF(ISNUMBER(SEARCH("BossLike",$E21)),1.18,1)*IF(ISNUMBER(SEARCH("Boss;",$E21&";")),1.25,1)*IF(ISNUMBER(SEARCH("Elite",$E21)),1.18,1)*IF(ISNUMBER(SEARCH("Ranged",$E21)),1.05,1)),0)&" / AS "&ROUND(VLOOKUP($A21,'06_怪物主表'!$A:$S,6,FALSE)*1.16,0) -> W15 HP 122 / Atk 21 / AS 42 | I21: 0.6-1.1秒 | J21: =IF(ISNUMBER($D21),ROUND(VLOOKUP($A21,'06_怪物主表'!$A:$S,18,FALSE)*$D21*VLOOKUP($A21,'06_怪物主表'!$A:$S,16,FALSE)*1.68*1.16*(IF(ISNUMBER(SEARCH("BossLike",$E21)),1.18,1)*IF(ISNUMBER(SEARCH("Boss;",$E21&";")),1.25,1)*IF(ISNUMBER(SEARCH("Elite",$E21)),1.18,1)*IF(ISNUMBER(SEARCH("Ranged",$E21)),1.05,1)),2),"节点固定") -> 0.08 | K21: 低频风筝远程。 DetectionRange 控制攻击释放入场，AttackRange 控制投射物最大距离。
A22: FlyForestEnemy | B22: 15-19 | C22: 12 | D22: 0.12 | E22: Ranged | F22: 边缘远程点 | G22: 默认 | H22: ="W15 HP "&ROUND(VLOOKUP($A22,'06_怪物主表'!$A:$S,4,FALSE)*3.8*(IF(ISNUMBER(SEARCH("BossLike",$E22)),1.45,1)*IF(ISNUMBER(SEARCH("Boss;",$E22&";")),1.6,1)*IF(ISNUMBER(SEARCH("Elite",$E22)),1.3,1)),0)&" / Atk "&ROUND(VLOOKUP($A22,'06_怪物主表'!$A:$S,5,FALSE)*1.68*(IF(ISNUMBER(SEARCH("BossLike",$E22)),1.18,1)*IF(ISNUMBER(SEARCH("Boss;",$E22&";")),1.25,1)*IF(ISNUMBER(SEARCH("Elite",$E22)),1.18,1)*IF(ISNUMBER(SEARCH("Ranged",$E22)),1.05,1)),0)&" / AS "&ROUND(VLOOKUP($A22,'06_怪物主表'!$A:$S,6,FALSE)*1.16,0) -> W15 HP 114 / Atk 19 / AS 56 | I22: 0.6-1.1秒 | J22: =IF(ISNUMBER($D22),ROUND(VLOOKUP($A22,'06_怪物主表'!$A:$S,18,FALSE)*$D22*VLOOKUP($A22,'06_怪物主表'!$A:$S,16,FALSE)*1.68*1.16*(IF(ISNUMBER(SEARCH("BossLike",$E22)),1.18,1)*IF(ISNUMBER(SEARCH("Boss;",$E22&";")),1.25,1)*IF(ISNUMBER(SEARCH("Elite",$E22)),1.18,1)*IF(ISNUMBER(SEARCH("Ranged",$E22)),1.05,1)),2),"节点固定") -> 0.18 | K22: 远程常规压力。 DetectionRange 控制攻击释放入场，AttackRange 控制投射物最大距离。
A23: EvilEyeEnemy | B23: 15-19 | C23: 8 | D23: 0.08 | E23: Ranged;Special | F23: 远程预警点 | G23: 默认 | H23: ="W15 HP "&ROUND(VLOOKUP($A23,'06_怪物主表'!$A:$S,4,FALSE)*3.8*(IF(ISNUMBER(SEARCH("BossLike",$E23)),1.45,1)*IF(ISNUMBER(SEARCH("Boss;",$E23&";")),1.6,1)*IF(ISNUMBER(SEARCH("Elite",$E23)),1.3,1)),0)&" / Atk "&ROUND(VLOOKUP($A23,'06_怪物主表'!$A:$S,5,FALSE)*1.68*(IF(ISNUMBER(SEARCH("BossLike",$E23)),1.18,1)*IF(ISNUMBER(SEARCH("Boss;",$E23&";")),1.25,1)*IF(ISNUMBER(SEARCH("Elite",$E23)),1.18,1)*IF(ISNUMBER(SEARCH("Ranged",$E23)),1.05,1)),0)&" / AS "&ROUND(VLOOKUP($A23,'06_怪物主表'!$A:$S,6,FALSE)*1.16,0) -> W15 HP 84 / Atk 28 / AS 49 | I23: 0.5-1.0秒 | J23: =IF(ISNUMBER($D23),ROUND(VLOOKUP($A23,'06_怪物主表'!$A:$S,18,FALSE)*$D23*VLOOKUP($A23,'06_怪物主表'!$A:$S,16,FALSE)*1.68*1.16*(IF(ISNUMBER(SEARCH("BossLike",$E23)),1.18,1)*IF(ISNUMBER(SEARCH("Boss;",$E23&";")),1.25,1)*IF(ISNUMBER(SEARCH("Elite",$E23)),1.18,1)*IF(ISNUMBER(SEARCH("Ranged",$E23)),1.05,1)),2),"节点固定") -> 0.16 | K23: 高威胁远程适量提高。 DetectionRange 控制攻击释放入场，AttackRange 控制投射物最大距离。
A24: SkeletonMeteorhammerEnemy | B24: 15-19 | C24: 10 | D24: 0.1 | E24: Heavy;Special | F24: 边缘慢速推进 | G24: 经验2；重型奖励池 | H24: ="W15 HP "&ROUND(VLOOKUP($A24,'06_怪物主表'!$A:$S,4,FALSE)*3.8*(IF(ISNUMBER(SEARCH("BossLike",$E24)),1.45,1)*IF(ISNUMBER(SEARCH("Boss;",$E24&";")),1.6,1)*IF(ISNUMBER(SEARCH("Elite",$E24)),1.3,1)),0)&" / Atk "&ROUND(VLOOKUP($A24,'06_怪物主表'!$A:$S,5,FALSE)*1.68*(IF(ISNUMBER(SEARCH("BossLike",$E24)),1.18,1)*IF(ISNUMBER(SEARCH("Boss;",$E24&";")),1.25,1)*IF(ISNUMBER(SEARCH("Elite",$E24)),1.18,1)*IF(ISNUMBER(SEARCH("Ranged",$E24)),1.05,1)),0)&" / AS "&ROUND(VLOOKUP($A24,'06_怪物主表'!$A:$S,6,FALSE)*1.16,0) -> W15 HP 266 / Atk 34 / AS 70 | I24: 4.0-6.5秒 | J24: =IF(ISNUMBER($D24),ROUND(VLOOKUP($A24,'06_怪物主表'!$A:$S,18,FALSE)*$D24*VLOOKUP($A24,'06_怪物主表'!$A:$S,16,FALSE)*1.68*1.16*(IF(ISNUMBER(SEARCH("BossLike",$E24)),1.18,1)*IF(ISNUMBER(SEARCH("Boss;",$E24&";")),1.25,1)*IF(ISNUMBER(SEARCH("Elite",$E24)),1.18,1)*IF(ISNUMBER(SEARCH("Ranged",$E24)),1.05,1)),2),"节点固定") -> 0.23 | K24: 一型保留但不再主导。
A25: SkeletonMeteorhammer2Enemy | B25: 15-19 | C25: 14 | D25: 0.14 | E25: Heavy;Special | F25: 峰值段/边缘推进 | G25: 经验2；重型奖励池 | H25: ="W15 HP "&ROUND(VLOOKUP($A25,'06_怪物主表'!$A:$S,4,FALSE)*3.8*(IF(ISNUMBER(SEARCH("BossLike",$E25)),1.45,1)*IF(ISNUMBER(SEARCH("Boss;",$E25&";")),1.6,1)*IF(ISNUMBER(SEARCH("Elite",$E25)),1.3,1)),0)&" / Atk "&ROUND(VLOOKUP($A25,'06_怪物主表'!$A:$S,5,FALSE)*1.68*(IF(ISNUMBER(SEARCH("BossLike",$E25)),1.18,1)*IF(ISNUMBER(SEARCH("Boss;",$E25&";")),1.25,1)*IF(ISNUMBER(SEARCH("Elite",$E25)),1.18,1)*IF(ISNUMBER(SEARCH("Ranged",$E25)),1.05,1)),0)&" / AS "&ROUND(VLOOKUP($A25,'06_怪物主表'!$A:$S,6,FALSE)*1.16,0) -> W15 HP 258 / Atk 30 / AS 67 | I25: 4.0-6.5秒 | J25: =IF(ISNUMBER($D25),ROUND(VLOOKUP($A25,'06_怪物主表'!$A:$S,18,FALSE)*$D25*VLOOKUP($A25,'06_怪物主表'!$A:$S,16,FALSE)*1.68*1.16*(IF(ISNUMBER(SEARCH("BossLike",$E25)),1.18,1)*IF(ISNUMBER(SEARCH("Boss;",$E25&";")),1.25,1)*IF(ISNUMBER(SEARCH("Elite",$E25)),1.18,1)*IF(ISNUMBER(SEARCH("Ranged",$E25)),1.05,1)),2),"节点固定") -> 0.36 | K25: 二型成为主要特殊近战。
A26: BlueGolemEnemy | B26: 15-19 | C26: 10 | D26: 0.1 | E26: Heavy;Special | F26: 峰值段定点/边缘冲锋 | G26: 经验2；重型奖励池 | H26: ="W15 HP "&ROUND(VLOOKUP($A26,'06_怪物主表'!$A:$S,4,FALSE)*3.8*(IF(ISNUMBER(SEARCH("BossLike",$E26)),1.45,1)*IF(ISNUMBER(SEARCH("Boss;",$E26&";")),1.6,1)*IF(ISNUMBER(SEARCH("Elite",$E26)),1.3,1)),0)&" / Atk "&ROUND(VLOOKUP($A26,'06_怪物主表'!$A:$S,5,FALSE)*1.68*(IF(ISNUMBER(SEARCH("BossLike",$E26)),1.18,1)*IF(ISNUMBER(SEARCH("Boss;",$E26&";")),1.25,1)*IF(ISNUMBER(SEARCH("Elite",$E26)),1.18,1)*IF(ISNUMBER(SEARCH("Ranged",$E26)),1.05,1)),0)&" / AS "&ROUND(VLOOKUP($A26,'06_怪物主表'!$A:$S,6,FALSE)*1.16,0) -> W15 HP 418 / Atk 44 / AS 49 | I26: 4.0-7.0秒 | J26: =IF(ISNUMBER($D26),ROUND(VLOOKUP($A26,'06_怪物主表'!$A:$S,18,FALSE)*$D26*VLOOKUP($A26,'06_怪物主表'!$A:$S,16,FALSE)*1.68*1.16*(IF(ISNUMBER(SEARCH("BossLike",$E26)),1.18,1)*IF(ISNUMBER(SEARCH("Boss;",$E26&";")),1.25,1)*IF(ISNUMBER(SEARCH("Elite",$E26)),1.18,1)*IF(ISNUMBER(SEARCH("Ranged",$E26)),1.05,1)),2),"节点固定") -> 0.24 | K26: 冲锋重型提高存在感。 DetectionRange 控制普攻入场，AttackRange 控制提交覆盖。
A27: OrangeGolemEnemy | B27: 15-19 | C27: 6 | D27: 0.06 | E27: Elite;Heavy | F27: 节点/峰值段定点 | G27: 精英奖励池 | H27: ="W15 HP "&ROUND(VLOOKUP($A27,'06_怪物主表'!$A:$S,4,FALSE)*3.8*(IF(ISNUMBER(SEARCH("BossLike",$E27)),1.45,1)*IF(ISNUMBER(SEARCH("Boss;",$E27&";")),1.6,1)*IF(ISNUMBER(SEARCH("Elite",$E27)),1.3,1)),0)&" / Atk "&ROUND(VLOOKUP($A27,'06_怪物主表'!$A:$S,5,FALSE)*1.68*(IF(ISNUMBER(SEARCH("BossLike",$E27)),1.18,1)*IF(ISNUMBER(SEARCH("Boss;",$E27&";")),1.25,1)*IF(ISNUMBER(SEARCH("Elite",$E27)),1.18,1)*IF(ISNUMBER(SEARCH("Ranged",$E27)),1.05,1)),0)&" / AS "&ROUND(VLOOKUP($A27,'06_怪物主表'!$A:$S,6,FALSE)*1.16,0) -> W15 HP 741 / Atk 67 / AS 44 | I27: 12-22秒 | J27: =IF(ISNUMBER($D27),ROUND(VLOOKUP($A27,'06_怪物主表'!$A:$S,18,FALSE)*$D27*VLOOKUP($A27,'06_怪物主表'!$A:$S,16,FALSE)*1.68*1.16*(IF(ISNUMBER(SEARCH("BossLike",$E27)),1.18,1)*IF(ISNUMBER(SEARCH("Boss;",$E27&";")),1.25,1)*IF(ISNUMBER(SEARCH("Elite",$E27)),1.18,1)*IF(ISNUMBER(SEARCH("Ranged",$E27)),1.05,1)),2),"节点固定") -> 0.37 | K27: 准精英低频出现。 DetectionRange 控制普攻入场，AttackRange 控制提交覆盖。
A28: MechaStoneBossEnemy | B28: 15-19 | C28: 0 | D28: 0.004 | E28: BossLike | F28: Boss入场点 | G28: 固定Boss奖励 | H28: ="W15 HP "&ROUND(VLOOKUP($A28,'06_怪物主表'!$A:$S,4,FALSE)*3.8*(IF(ISNUMBER(SEARCH("BossLike",$E28)),1.45,1)*IF(ISNUMBER(SEARCH("Boss;",$E28&";")),1.6,1)*IF(ISNUMBER(SEARCH("Elite",$E28)),1.3,1)),0)&" / Atk "&ROUND(VLOOKUP($A28,'06_怪物主表'!$A:$S,5,FALSE)*1.68*(IF(ISNUMBER(SEARCH("BossLike",$E28)),1.18,1)*IF(ISNUMBER(SEARCH("Boss;",$E28&";")),1.25,1)*IF(ISNUMBER(SEARCH("Elite",$E28)),1.18,1)*IF(ISNUMBER(SEARCH("Ranged",$E28)),1.05,1)),0)&" / AS "&ROUND(VLOOKUP($A28,'06_怪物主表'!$A:$S,6,FALSE)*1.16,0) -> W15 HP 19285 / Atk 83 / AS 41 | I28: 45-70秒 | J28: =IF(ISNUMBER($D28),ROUND(VLOOKUP($A28,'06_怪物主表'!$A:$S,18,FALSE)*$D28*VLOOKUP($A28,'06_怪物主表'!$A:$S,16,FALSE)*1.68*1.16*(IF(ISNUMBER(SEARCH("BossLike",$E28)),1.18,1)*IF(ISNUMBER(SEARCH("Boss;",$E28&";")),1.25,1)*IF(ISNUMBER(SEARCH("Elite",$E28)),1.18,1)*IF(ISNUMBER(SEARCH("Ranged",$E28)),1.05,1)),2),"节点固定") -> 0.04 | K28: Boss节点固定；射击倍率需同时覆盖释放距离和投射物最大飞行距离；激光范围走技能长度。
A29: SkeletonEnemy | B29: 20+ | C29: 15 | D29: 0.15 | E29: Normal | F29: 边缘持续生成 | G29: 默认 | H29: ="W20 HP "&ROUND(VLOOKUP($A29,'06_怪物主表'!$A:$S,4,FALSE)*6*(IF(ISNUMBER(SEARCH("BossLike",$E29)),1.45,1)*IF(ISNUMBER(SEARCH("Boss;",$E29&";")),1.6,1)*IF(ISNUMBER(SEARCH("Elite",$E29)),1.3,1)),0)&" / Atk "&ROUND(VLOOKUP($A29,'06_怪物主表'!$A:$S,5,FALSE)*2.1*(IF(ISNUMBER(SEARCH("BossLike",$E29)),1.18,1)*IF(ISNUMBER(SEARCH("Boss;",$E29&";")),1.25,1)*IF(ISNUMBER(SEARCH("Elite",$E29)),1.18,1)*IF(ISNUMBER(SEARCH("Ranged",$E29)),1.05,1)),0)&" / AS "&ROUND(VLOOKUP($A29,'06_怪物主表'!$A:$S,6,FALSE)*1.25,0) -> W20 HP 192 / Atk 32 / AS 90 | I29: 0.4-0.9秒 | J29: =IF(ISNUMBER($D29),ROUND(VLOOKUP($A29,'06_怪物主表'!$A:$S,18,FALSE)*$D29*VLOOKUP($A29,'06_怪物主表'!$A:$S,16,FALSE)*2.1*1.25*(IF(ISNUMBER(SEARCH("BossLike",$E29)),1.18,1)*IF(ISNUMBER(SEARCH("Boss;",$E29&";")),1.25,1)*IF(ISNUMBER(SEARCH("Elite",$E29)),1.18,1)*IF(ISNUMBER(SEARCH("Ranged",$E29)),1.05,1)),2),"节点固定") -> 0.37 | K29: 终局基础数量压力。
A30: EvilSlimeEnemy | B30: 20+ | C30: 11 | D30: 0.11 | E30: Fast | F30: 侧翼夹击 | G30: 快速怪掉率 | H30: ="W20 HP "&ROUND(VLOOKUP($A30,'06_怪物主表'!$A:$S,4,FALSE)*6*(IF(ISNUMBER(SEARCH("BossLike",$E30)),1.45,1)*IF(ISNUMBER(SEARCH("Boss;",$E30&";")),1.6,1)*IF(ISNUMBER(SEARCH("Elite",$E30)),1.3,1)),0)&" / Atk "&ROUND(VLOOKUP($A30,'06_怪物主表'!$A:$S,5,FALSE)*2.1*(IF(ISNUMBER(SEARCH("BossLike",$E30)),1.18,1)*IF(ISNUMBER(SEARCH("Boss;",$E30&";")),1.25,1)*IF(ISNUMBER(SEARCH("Elite",$E30)),1.18,1)*IF(ISNUMBER(SEARCH("Ranged",$E30)),1.05,1)),0)&" / AS "&ROUND(VLOOKUP($A30,'06_怪物主表'!$A:$S,6,FALSE)*1.25,0) -> W20 HP 144 / Atk 21 / AS 125 | I30: 0.3-0.7秒 | J30: =IF(ISNUMBER($D30),ROUND(VLOOKUP($A30,'06_怪物主表'!$A:$S,18,FALSE)*$D30*VLOOKUP($A30,'06_怪物主表'!$A:$S,16,FALSE)*2.1*1.25*(IF(ISNUMBER(SEARCH("BossLike",$E30)),1.18,1)*IF(ISNUMBER(SEARCH("Boss;",$E30&";")),1.25,1)*IF(ISNUMBER(SEARCH("Elite",$E30)),1.18,1)*IF(ISNUMBER(SEARCH("Ranged",$E30)),1.05,1)),2),"节点固定") -> 0.58 | K30: 控制接触压力上限。
A31: WormEnemy | B31: 20+ | C31: 6 | D31: 0.06 | E31: Ranged | F31: 边缘远程点 | G31: 默认 | H31: ="W20 HP "&ROUND(VLOOKUP($A31,'06_怪物主表'!$A:$S,4,FALSE)*6*(IF(ISNUMBER(SEARCH("BossLike",$E31)),1.45,1)*IF(ISNUMBER(SEARCH("Boss;",$E31&";")),1.6,1)*IF(ISNUMBER(SEARCH("Elite",$E31)),1.3,1)),0)&" / Atk "&ROUND(VLOOKUP($A31,'06_怪物主表'!$A:$S,5,FALSE)*2.1*(IF(ISNUMBER(SEARCH("BossLike",$E31)),1.18,1)*IF(ISNUMBER(SEARCH("Boss;",$E31&";")),1.25,1)*IF(ISNUMBER(SEARCH("Elite",$E31)),1.18,1)*IF(ISNUMBER(SEARCH("Ranged",$E31)),1.05,1)),0)&" / AS "&ROUND(VLOOKUP($A31,'06_怪物主表'!$A:$S,6,FALSE)*1.25,0) -> W20 HP 192 / Atk 26 / AS 45 | I31: 0.5-1.0秒 | J31: =IF(ISNUMBER($D31),ROUND(VLOOKUP($A31,'06_怪物主表'!$A:$S,18,FALSE)*$D31*VLOOKUP($A31,'06_怪物主表'!$A:$S,16,FALSE)*2.1*1.25*(IF(ISNUMBER(SEARCH("BossLike",$E31)),1.18,1)*IF(ISNUMBER(SEARCH("Boss;",$E31&";")),1.25,1)*IF(ISNUMBER(SEARCH("Elite",$E31)),1.18,1)*IF(ISNUMBER(SEARCH("Ranged",$E31)),1.05,1)),2),"节点固定") -> 0.08 | K31: 低频风筝远程。 DetectionRange 控制攻击释放入场，AttackRange 控制投射物最大距离。
A32: FlyForestEnemy | B32: 20+ | C32: 10 | D32: 0.1 | E32: Ranged | F32: 边缘远程点 | G32: 默认 | H32: ="W20 HP "&ROUND(VLOOKUP($A32,'06_怪物主表'!$A:$S,4,FALSE)*6*(IF(ISNUMBER(SEARCH("BossLike",$E32)),1.45,1)*IF(ISNUMBER(SEARCH("Boss;",$E32&";")),1.6,1)*IF(ISNUMBER(SEARCH("Elite",$E32)),1.3,1)),0)&" / Atk "&ROUND(VLOOKUP($A32,'06_怪物主表'!$A:$S,5,FALSE)*2.1*(IF(ISNUMBER(SEARCH("BossLike",$E32)),1.18,1)*IF(ISNUMBER(SEARCH("Boss;",$E32&";")),1.25,1)*IF(ISNUMBER(SEARCH("Elite",$E32)),1.18,1)*IF(ISNUMBER(SEARCH("Ranged",$E32)),1.05,1)),0)&" / AS "&ROUND(VLOOKUP($A32,'06_怪物主表'!$A:$S,6,FALSE)*1.25,0) -> W20 HP 180 / Atk 24 / AS 60 | I32: 0.5-1.0秒 | J32: =IF(ISNUMBER($D32),ROUND(VLOOKUP($A32,'06_怪物主表'!$A:$S,18,FALSE)*$D32*VLOOKUP($A32,'06_怪物主表'!$A:$S,16,FALSE)*2.1*1.25*(IF(ISNUMBER(SEARCH("BossLike",$E32)),1.18,1)*IF(ISNUMBER(SEARCH("Boss;",$E32&";")),1.25,1)*IF(ISNUMBER(SEARCH("Elite",$E32)),1.18,1)*IF(ISNUMBER(SEARCH("Ranged",$E32)),1.05,1)),2),"节点固定") -> 0.2 | K32: 终局远程基础项。 DetectionRange 控制攻击释放入场，AttackRange 控制投射物最大距离。
A33: EvilEyeEnemy | B33: 20+ | C33: 8 | D33: 0.08 | E33: Ranged;Special | F33: 远程预警点 | G33: 默认 | H33: ="W20 HP "&ROUND(VLOOKUP($A33,'06_怪物主表'!$A:$S,4,FALSE)*6*(IF(ISNUMBER(SEARCH("BossLike",$E33)),1.45,1)*IF(ISNUMBER(SEARCH("Boss;",$E33&";")),1.6,1)*IF(ISNUMBER(SEARCH("Elite",$E33)),1.3,1)),0)&" / Atk "&ROUND(VLOOKUP($A33,'06_怪物主表'!$A:$S,5,FALSE)*2.1*(IF(ISNUMBER(SEARCH("BossLike",$E33)),1.18,1)*IF(ISNUMBER(SEARCH("Boss;",$E33&";")),1.25,1)*IF(ISNUMBER(SEARCH("Elite",$E33)),1.18,1)*IF(ISNUMBER(SEARCH("Ranged",$E33)),1.05,1)),0)&" / AS "&ROUND(VLOOKUP($A33,'06_怪物主表'!$A:$S,6,FALSE)*1.25,0) -> W20 HP 132 / Atk 35 / AS 53 | I33: 0.4-0.9秒 | J33: =IF(ISNUMBER($D33),ROUND(VLOOKUP($A33,'06_怪物主表'!$A:$S,18,FALSE)*$D33*VLOOKUP($A33,'06_怪物主表'!$A:$S,16,FALSE)*2.1*1.25*(IF(ISNUMBER(SEARCH("BossLike",$E33)),1.18,1)*IF(ISNUMBER(SEARCH("Boss;",$E33&";")),1.25,1)*IF(ISNUMBER(SEARCH("Elite",$E33)),1.18,1)*IF(ISNUMBER(SEARCH("Ranged",$E33)),1.05,1)),2),"节点固定") -> 0.21 | K33: 终局高威胁远程。 DetectionRange 控制攻击释放入场，AttackRange 控制投射物最大距离。
A34: SkeletonMeteorhammerEnemy | B34: 20+ | C34: 7 | D34: 0.07 | E34: Heavy;Special | F34: 边缘推进 | G34: 经验2；重型奖励池 | H34: ="W20 HP "&ROUND(VLOOKUP($A34,'06_怪物主表'!$A:$S,4,FALSE)*6*(IF(ISNUMBER(SEARCH("BossLike",$E34)),1.45,1)*IF(ISNUMBER(SEARCH("Boss;",$E34&";")),1.6,1)*IF(ISNUMBER(SEARCH("Elite",$E34)),1.3,1)),0)&" / Atk "&ROUND(VLOOKUP($A34,'06_怪物主表'!$A:$S,5,FALSE)*2.1*(IF(ISNUMBER(SEARCH("BossLike",$E34)),1.18,1)*IF(ISNUMBER(SEARCH("Boss;",$E34&";")),1.25,1)*IF(ISNUMBER(SEARCH("Elite",$E34)),1.18,1)*IF(ISNUMBER(SEARCH("Ranged",$E34)),1.05,1)),0)&" / AS "&ROUND(VLOOKUP($A34,'06_怪物主表'!$A:$S,6,FALSE)*1.25,0) -> W20 HP 420 / Atk 42 / AS 75 | I34: 4.5-7.5秒 | J34: =IF(ISNUMBER($D34),ROUND(VLOOKUP($A34,'06_怪物主表'!$A:$S,18,FALSE)*$D34*VLOOKUP($A34,'06_怪物主表'!$A:$S,16,FALSE)*2.1*1.25*(IF(ISNUMBER(SEARCH("BossLike",$E34)),1.18,1)*IF(ISNUMBER(SEARCH("Boss;",$E34&";")),1.25,1)*IF(ISNUMBER(SEARCH("Elite",$E34)),1.18,1)*IF(ISNUMBER(SEARCH("Ranged",$E34)),1.05,1)),2),"节点固定") -> 0.22 | K34: 一型低频保留。
A35: SkeletonMeteorhammer2Enemy | B35: 20+ | C35: 15 | D35: 0.15 | E35: Heavy;Special | F35: 峰值段/边缘推进 | G35: 经验2；重型奖励池 | H35: ="W20 HP "&ROUND(VLOOKUP($A35,'06_怪物主表'!$A:$S,4,FALSE)*6*(IF(ISNUMBER(SEARCH("BossLike",$E35)),1.45,1)*IF(ISNUMBER(SEARCH("Boss;",$E35&";")),1.6,1)*IF(ISNUMBER(SEARCH("Elite",$E35)),1.3,1)),0)&" / Atk "&ROUND(VLOOKUP($A35,'06_怪物主表'!$A:$S,5,FALSE)*2.1*(IF(ISNUMBER(SEARCH("BossLike",$E35)),1.18,1)*IF(ISNUMBER(SEARCH("Boss;",$E35&";")),1.25,1)*IF(ISNUMBER(SEARCH("Elite",$E35)),1.18,1)*IF(ISNUMBER(SEARCH("Ranged",$E35)),1.05,1)),0)&" / AS "&ROUND(VLOOKUP($A35,'06_怪物主表'!$A:$S,6,FALSE)*1.25,0) -> W20 HP 408 / Atk 38 / AS 73 | I35: 4.5-7.5秒 | J35: =IF(ISNUMBER($D35),ROUND(VLOOKUP($A35,'06_怪物主表'!$A:$S,18,FALSE)*$D35*VLOOKUP($A35,'06_怪物主表'!$A:$S,16,FALSE)*2.1*1.25*(IF(ISNUMBER(SEARCH("BossLike",$E35)),1.18,1)*IF(ISNUMBER(SEARCH("Boss;",$E35&";")),1.25,1)*IF(ISNUMBER(SEARCH("Elite",$E35)),1.18,1)*IF(ISNUMBER(SEARCH("Ranged",$E35)),1.05,1)),2),"节点固定") -> 0.52 | K35: 终局主要特殊近战。
A36: BlueGolemEnemy | B36: 20+ | C36: 13 | D36: 0.13 | E36: Heavy;Special | F36: 峰值段定点/边缘冲锋 | G36: 经验2；重型奖励池 | H36: ="W20 HP "&ROUND(VLOOKUP($A36,'06_怪物主表'!$A:$S,4,FALSE)*6*(IF(ISNUMBER(SEARCH("BossLike",$E36)),1.45,1)*IF(ISNUMBER(SEARCH("Boss;",$E36&";")),1.6,1)*IF(ISNUMBER(SEARCH("Elite",$E36)),1.3,1)),0)&" / Atk "&ROUND(VLOOKUP($A36,'06_怪物主表'!$A:$S,5,FALSE)*2.1*(IF(ISNUMBER(SEARCH("BossLike",$E36)),1.18,1)*IF(ISNUMBER(SEARCH("Boss;",$E36&";")),1.25,1)*IF(ISNUMBER(SEARCH("Elite",$E36)),1.18,1)*IF(ISNUMBER(SEARCH("Ranged",$E36)),1.05,1)),0)&" / AS "&ROUND(VLOOKUP($A36,'06_怪物主表'!$A:$S,6,FALSE)*1.25,0) -> W20 HP 660 / Atk 55 / AS 53 | I36: 4.5-8.0秒 | J36: =IF(ISNUMBER($D36),ROUND(VLOOKUP($A36,'06_怪物主表'!$A:$S,18,FALSE)*$D36*VLOOKUP($A36,'06_怪物主表'!$A:$S,16,FALSE)*2.1*1.25*(IF(ISNUMBER(SEARCH("BossLike",$E36)),1.18,1)*IF(ISNUMBER(SEARCH("Boss;",$E36&";")),1.25,1)*IF(ISNUMBER(SEARCH("Elite",$E36)),1.18,1)*IF(ISNUMBER(SEARCH("Ranged",$E36)),1.05,1)),2),"节点固定") -> 0.42 | K36: 终局冲锋重型。 DetectionRange 控制普攻入场，AttackRange 控制提交覆盖。
A37: OrangeGolemEnemy | B37: 20+ | C37: 8 | D37: 0.08 | E37: Elite;Heavy | F37: 精英入场点 | G37: 精英奖励池 | H37: ="W20 HP "&ROUND(VLOOKUP($A37,'06_怪物主表'!$A:$S,4,FALSE)*6*(IF(ISNUMBER(SEARCH("BossLike",$E37)),1.45,1)*IF(ISNUMBER(SEARCH("Boss;",$E37&";")),1.6,1)*IF(ISNUMBER(SEARCH("Elite",$E37)),1.3,1)),0)&" / Atk "&ROUND(VLOOKUP($A37,'06_怪物主表'!$A:$S,5,FALSE)*2.1*(IF(ISNUMBER(SEARCH("BossLike",$E37)),1.18,1)*IF(ISNUMBER(SEARCH("Boss;",$E37&";")),1.25,1)*IF(ISNUMBER(SEARCH("Elite",$E37)),1.18,1)*IF(ISNUMBER(SEARCH("Ranged",$E37)),1.05,1)),0)&" / AS "&ROUND(VLOOKUP($A37,'06_怪物主表'!$A:$S,6,FALSE)*1.25,0) -> W20 HP 1170 / Atk 84 / AS 48 | I37: 15-28秒 | J37: =IF(ISNUMBER($D37),ROUND(VLOOKUP($A37,'06_怪物主表'!$A:$S,18,FALSE)*$D37*VLOOKUP($A37,'06_怪物主表'!$A:$S,16,FALSE)*2.1*1.25*(IF(ISNUMBER(SEARCH("BossLike",$E37)),1.18,1)*IF(ISNUMBER(SEARCH("Boss;",$E37&";")),1.25,1)*IF(ISNUMBER(SEARCH("Elite",$E37)),1.18,1)*IF(ISNUMBER(SEARCH("Ranged",$E37)),1.05,1)),2),"节点固定") -> 0.67 | K37: 终局精英压力。 DetectionRange 控制普攻入场，AttackRange 控制提交覆盖。
A38: MechaStoneBossEnemy | B38: 20+ | C38: 0 | D38: 0.003 | E38: BossLike;Boss | F38: Boss入场点 | G38: 固定Boss奖励 | H38: ="W20 HP "&ROUND(VLOOKUP($A38,'06_怪物主表'!$A:$S,4,FALSE)*6*(IF(ISNUMBER(SEARCH("BossLike",$E38)),1.45,1)*IF(ISNUMBER(SEARCH("Boss;",$E38&";")),1.6,1)*IF(ISNUMBER(SEARCH("Elite",$E38)),1.3,1)),0)&" / Atk "&ROUND(VLOOKUP($A38,'06_怪物主表'!$A:$S,5,FALSE)*2.1*(IF(ISNUMBER(SEARCH("BossLike",$E38)),1.18,1)*IF(ISNUMBER(SEARCH("Boss;",$E38&";")),1.25,1)*IF(ISNUMBER(SEARCH("Elite",$E38)),1.18,1)*IF(ISNUMBER(SEARCH("Ranged",$E38)),1.05,1)),0)&" / AS "&ROUND(VLOOKUP($A38,'06_怪物主表'!$A:$S,6,FALSE)*1.25,0) -> W20 HP 48720 / Atk 130 / AS 44 | I38: 60-90秒 | J38: =IF(ISNUMBER($D38),ROUND(VLOOKUP($A38,'06_怪物主表'!$A:$S,18,FALSE)*$D38*VLOOKUP($A38,'06_怪物主表'!$A:$S,16,FALSE)*2.1*1.25*(IF(ISNUMBER(SEARCH("BossLike",$E38)),1.18,1)*IF(ISNUMBER(SEARCH("Boss;",$E38&";")),1.25,1)*IF(ISNUMBER(SEARCH("Elite",$E38)),1.18,1)*IF(ISNUMBER(SEARCH("Ranged",$E38)),1.05,1)),2),"节点固定") -> 0.05 | K38: Boss节点固定；射击倍率需同时覆盖释放距离和投射物最大飞行距离；激光范围走技能长度。

Sheet 08_波次
A1: 波次ID | B1: 持续时间 | C1: 目标玩家状态 | D1: 总刷怪数量 | E1: 每分钟密度 | F1: 时间分布 | G1: 目标同屏数量 | H1: 波次总生命池 | I1: 清场需求DPS | J1: 波次总伤害压力 | K1: 普通怪结构 | L1: 精英节奏 | M1: Boss节奏 | N1: 生成位置 | O1: 掉落/经济目标 | P1: 备注
A2: Wave_001 | B2: 40 | C2: Lv1-2；0-1件商品；武器Lv1 | D2: 50 | E2: =ROUND(D2/B2*60,0) -> 75 | F2: 起压0-20%/12%；主压20-65%/50%；峰值65-85%/28%；收尾85-100%/10% | G2: 10-14 | H2: 1400 | I2: =ROUND(H2/B2,0) -> 35 | J2: 180 | K2: 骷髅70%/史莱姆30% | L2: 无 | M2: 无 | N2: 边缘低密度 | O2: 经验约50；金币15-25 | P2: 教学清怪与拾取。
A3: Wave_002 | B3: 40 | C3: Lv2-3；0-1件商品；武器Lv1 | D3: 62 | E3: =ROUND(D3/B3*60,0) -> 93 | F3: 起压0-20%/12%；主压20-65%/50%；峰值65-85%/28%；收尾85-100%/10% | G3: 12-16 | H3: 2000 | I3: =ROUND(H3/B3,0) -> 50 | J3: 240 | K3: 骷髅68%/史莱姆32% | L3: 无 | M3: 无 | N3: 边缘低密度 | O3: 经验约62；金币18-28 | P3: 提高包围密度。
A4: Wave_003 | B4: 40 | C4: Lv3-4；1件商品；武器Lv1 | D4: 75 | E4: =ROUND(D4/B4*60,0) -> 113 | F4: 起压0-20%/12%；主压20-65%/50%；峰值65-85%/28%；收尾85-100%/10% | G4: 14-18 | H4: 2900 | I4: =ROUND(H4/B4,0) -> 73 | J4: 330 | K4: 骷髅60%/史莱姆35%/流星锤5% | L4: 无 | M4: 无 | N4: 边缘+少量侧翼 | O4: 经验约78；金币22-34 | P4: 开始出现低频重型。
A5: Wave_004 | B5: 40 | C5: Lv4-5；1-2件商品；武器Lv1-Lv2 | D5: 85 | E5: =ROUND(D5/B5*60,0) -> 128 | F5: 起压0-20%/12%；主压20-65%/50%；峰值65-85%/28%；收尾85-100%/10% | G5: 16-22 | H5: 4100 | I5: =ROUND(H5/B5,0) -> 103 | J5: 480 | K5: 骷髅55%/史莱姆35%/流星锤10% | L5: 无 | M5: 无 | N5: 边缘+侧翼 | O5: 经验约92；金币28-42 | P5: 进入第一次商店取舍前。
A6: Wave_005 | B6: 50 | C6: Lv6-7；累计金币120-180；购买4-6；主力Lv2 | D6: 115 | E6: =ROUND(D6/B6*60,0) -> 138 | F6: 缓冲0-15%/8%；入场15-30%/12%；混压30-75%/60%；终段75-100%/20% | G6: 20-30 | H6: 8200 | I6: =ROUND(H6/B6,0) -> 164 | J6: 760 | K6: 骷髅35%/史莱姆25%/蠕虫13%/飞虫10%/流星锤15%/邪眼2% | L6: 无 | M6: 无 | N6: 边缘+节点定点 | O6: 经验约125；金币35-55；小宝箱低概率 | P6: 第一次小压力节点。
A7: Wave_006 | B7: 45 | C7: Lv7-8；购买5-7；主力Lv2 | D7: 120 | E7: =ROUND(D7/B7*60,0) -> 160 | F7: 起压0-20%/12%；主压20-65%/50%；峰值65-85%/28%；收尾85-100%/10% | G7: 22-32 | H7: 9500 | I7: =ROUND(H7/B7,0) -> 211 | J7: 850 | K7: 骷髅35%/史莱姆25%/蠕虫13%/飞虫10%/流星锤15%/邪眼2% | L7: 无 | M7: 无 | N7: 边缘+侧翼 | O7: 经验约120；金币40-60 | P7: 稳定构筑过渡。
A8: Wave_007 | B8: 45 | C8: Lv8-9；饰品3-5；主力Lv2 | D8: 138 | E8: =ROUND(D8/B8*60,0) -> 184 | F8: 起压0-20%/12%；主压20-65%/50%；峰值65-85%/28%；收尾85-100%/10% | G8: 24-34 | H8: 12000 | I8: =ROUND(H8/B8,0) -> 267 | J8: 1050 | K8: 骷髅32%/史莱姆25%/蠕虫13%/飞虫12%/流星锤16%/邪眼2% | L8: 无 | M8: 无 | N8: 边缘+远程预警点 | O8: 经验约140；金币45-70 | P8: 远程少量进入常规池。
A9: Wave_008 | B9: 45 | C9: Lv9-10；购买7-10；主力Lv2-Lv3 | D9: 155 | E9: =ROUND(D9/B9*60,0) -> 207 | F9: 起压0-20%/12%；主压20-65%/50%；峰值65-85%/28%；收尾85-100%/10% | G9: 28-36 | H9: 15500 | I9: =ROUND(H9/B9,0) -> 344 | J9: 1300 | K9: 骷髅30%/史莱姆25%/蠕虫13%/飞虫12%/流星锤16%/邪眼4% | L9: 无 | M9: 无 | N9: 边缘+侧翼 | O9: 经验约158；金币55-85 | P9: 密度明显提高。
A10: Wave_009 | B10: 45 | C10: Lv10-11；准备10波节点；主力接近Lv3 | D10: 170 | E10: =ROUND(D10/B10*60,0) -> 227 | F10: 起压0-20%/12%；主压20-65%/50%；峰值65-85%/28%；收尾85-100%/10% | G10: 32-38 | H10: 19500 | I10: =ROUND(H10/B10,0) -> 433 | J10: 1550 | K10: 骷髅28%/史莱姆24%/蠕虫13%/飞虫13%/流星锤16%/邪眼6% | L10: 无 | M10: 无 | N10: 边缘+峰值夹击 | O10: 经验约175；金币65-95 | P10: 10波前的输出检验。
A11: Wave_010 | B11: 60 | C11: Lv10-12；累计金币360-540；主力Lv3 | D11: 215 | E11: =ROUND(D11/B11*60,0) -> 215 | F11: 缓冲0-15%/8%；入场15-30%/12%；混压30-75%/60%；终段75-100%/20% | G11: 34-50 | H11: 35000 | I11: =ROUND(H11/B11,0) -> 583 | J11: 2200 | K11: 骷髅24%/史莱姆18%/蠕虫11%/飞虫12%/邪眼6%/流星锤14%/流星锤二型9%/蓝石头人5% | L11: 蓝石头人低频；可追加橙石头人预告 | M11: 机械石像Boss，15-30%入场 | N11: Boss点+边缘混刷 | O11: 经验约230；金币85-125；Boss奖励 | P11: 首个Boss或强节点。
A12: Wave_011 | B12: 50 | C12: Lv12-13；饰品6-9；副武器Lv2 | D12: 210 | E12: =ROUND(D12/B12*60,0) -> 252 | F12: 起压0-20%/12%；主压20-65%/50%；峰值65-85%/28%；收尾85-100%/10% | G12: 36-52 | H12: 42000 | I12: =ROUND(H12/B12,0) -> 840 | J12: 2400 | K12: 骷髅24%/史莱姆18%/蠕虫11%/飞虫12%/邪眼6%/流星锤14%/流星锤二型9%/蓝石头人5% | L12: 蓝石头人低频 | M12: 无 | N12: 边缘+远程预警点 | O12: 经验约215；金币80-120 | P12: 中期常规压力。
A13: Wave_012 | B13: 50 | C13: Lv13-14；购买12-16；主力Lv3 | D13: 240 | E13: =ROUND(D13/B13*60,0) -> 288 | F13: 起压0-20%/12%；主压20-65%/50%；峰值65-85%/28%；收尾85-100%/10% | G13: 40-56 | H13: 54000 | I13: =ROUND(H13/B13,0) -> 1080 | J13: 3000 | K13: 骷髅22%/史莱姆18%/蠕虫11%/飞虫12%/邪眼7%/流星锤14%/流星锤二型10%/蓝石头人6% | L13: 蓝石头人低频 | M13: 无 | N13: 边缘+侧翼 | O13: 经验约248；金币90-135 | P13: 提高生命池压力。
... A21: Wave_020 | B21: 75 | C21: Lv20-23；累计金币1300-1900；主力Lv4；至少2把副武器Lv3 | D21: 560 | E21: =ROUND(D21/B21*60,0) -> 448 | F21: 缓冲0-15%/8%；入场15-30%/12%；混压30-75%/60%；终段75-100%/20% | G21: 75-110 | H21: 420000 | I21: =ROUND(H21/B21,0) -> 5600 | J21: 13000 | K21: 骷髅15%/史莱姆11%/蠕虫6%/飞虫10%/邪眼8%/流星锤7%/流星锤二型15%/蓝石头人13%/橙石头人8% | L21: 橙石头人分三段入场 | M21: 机械石像Boss，15-30%入场，终段压力提高 | N21: Boss点+环形边缘+远程预警 | O21: 经验约600；金币220-320；Boss奖励 | P21: 终局Boss+密度压力。

Sheet 09_商店内容池
A1: 池条目ID | B1: 内容类型 | C1: 内容ID | D1: 品质/等级 | E1: 开放波次 | F1: 关闭波次 | G1: 基础权重 | H1: 幸运系数 | I1: 内容池价格倍率 | J1: 重复规则 | K1: 替代规则 | L1: 期望入口 | M1: 备注
A2: Shop_AccessoryQuality_Common_01_04 | B2: 饰品品质权重 | C2: AccessoryPool_Common | D2: Common | E2: 1 | F2: 4 | G2: 85 | H2: -0.4 | I2: 1 | J2: 按具体饰品重复口径 | K2: 基础权重为0时不开放；唯一/上限达成则剔除 | L2: 商店饰品格 | M2: 品质层权重，用于幸运修正和波次开放。
A3: Shop_AccessoryQuality_Rare_01_04 | B3: 饰品品质权重 | C3: AccessoryPool_Rare | D3: Rare | E3: 1 | F3: 4 | G3: 15 | H3: 0.4 | I3: 1.05 | J3: 按具体饰品重复口径 | K3: 基础权重为0时不开放；唯一/上限达成则剔除 | L3: 商店饰品格 | M3: 品质层权重，用于幸运修正和波次开放。
A4: Shop_AccessoryQuality_Epic_01_04 | B4: 饰品品质权重 | C4: AccessoryPool_Epic | D4: Epic | E4: 1 | F4: 4 | G4: 0 | H4: 0.9 | I4: 1.1 | J4: 按具体饰品重复口径 | K4: 基础权重为0时不开放；唯一/上限达成则剔除 | L4: 商店饰品格 | M4: 品质层权重，用于幸运修正和波次开放。
A5: Shop_AccessoryQuality_Legendary_01_04 | B5: 饰品品质权重 | C5: AccessoryPool_Legendary | D5: Legendary | E5: 1 | F5: 4 | G5: 0 | H5: 1.4 | I5: 1.2 | J5: 按具体饰品重复口径 | K5: 基础权重为0时不开放；唯一/上限达成则剔除 | L5: 商店饰品格 | M5: 品质层权重，用于幸运修正和波次开放。
A6: Shop_AccessoryQuality_Common_05_09 | B6: 饰品品质权重 | C6: AccessoryPool_Common | D6: Common | E6: 5 | F6: 9 | G6: 65 | H6: -0.4 | I6: 1 | J6: 按具体饰品重复口径 | K6: 基础权重为0时不开放；唯一/上限达成则剔除 | L6: 商店饰品格 | M6: 品质层权重，用于幸运修正和波次开放。
A7: Shop_AccessoryQuality_Rare_05_09 | B7: 饰品品质权重 | C7: AccessoryPool_Rare | D7: Rare | E7: 5 | F7: 9 | G7: 30 | H7: 0.4 | I7: 1.05 | J7: 按具体饰品重复口径 | K7: 基础权重为0时不开放；唯一/上限达成则剔除 | L7: 商店饰品格 | M7: 品质层权重，用于幸运修正和波次开放。
A8: Shop_AccessoryQuality_Epic_05_09 | B8: 饰品品质权重 | C8: AccessoryPool_Epic | D8: Epic | E8: 5 | F8: 9 | G8: 5 | H8: 0.9 | I8: 1.1 | J8: 按具体饰品重复口径 | K8: 基础权重为0时不开放；唯一/上限达成则剔除 | L8: 商店饰品格 | M8: 品质层权重，用于幸运修正和波次开放。
A9: Shop_AccessoryQuality_Legendary_05_09 | B9: 饰品品质权重 | C9: AccessoryPool_Legendary | D9: Legendary | E9: 5 | F9: 9 | G9: 0 | H9: 1.4 | I9: 1.2 | J9: 按具体饰品重复口径 | K9: 基础权重为0时不开放；唯一/上限达成则剔除 | L9: 商店饰品格 | M9: 品质层权重，用于幸运修正和波次开放。
A10: Shop_AccessoryQuality_Common_10_14 | B10: 饰品品质权重 | C10: AccessoryPool_Common | D10: Common | E10: 10 | F10: 14 | G10: 45 | H10: -0.4 | I10: 1 | J10: 按具体饰品重复口径 | K10: 基础权重为0时不开放；唯一/上限达成则剔除 | L10: 商店饰品格 | M10: 品质层权重，用于幸运修正和波次开放。
A11: Shop_AccessoryQuality_Rare_10_14 | B11: 饰品品质权重 | C11: AccessoryPool_Rare | D11: Rare | E11: 10 | F11: 14 | G11: 40 | H11: 0.4 | I11: 1.05 | J11: 按具体饰品重复口径 | K11: 基础权重为0时不开放；唯一/上限达成则剔除 | L11: 商店饰品格 | M11: 品质层权重，用于幸运修正和波次开放。
A12: Shop_AccessoryQuality_Epic_10_14 | B12: 饰品品质权重 | C12: AccessoryPool_Epic | D12: Epic | E12: 10 | F12: 14 | G12: 14 | H12: 0.9 | I12: 1.1 | J12: 按具体饰品重复口径 | K12: 基础权重为0时不开放；唯一/上限达成则剔除 | L12: 商店饰品格 | M12: 品质层权重，用于幸运修正和波次开放。
A13: Shop_AccessoryQuality_Legendary_10_14 | B13: 饰品品质权重 | C13: AccessoryPool_Legendary | D13: Legendary | E13: 10 | F13: 14 | G13: 1 | H13: 1.4 | I13: 1.2 | J13: 按具体饰品重复口径 | K13: 基础权重为0时不开放；唯一/上限达成则剔除 | L13: 商店饰品格 | M13: 品质层权重，用于幸运修正和波次开放。
... A17: Shop_AccessoryQuality_Legendary_15_19 | B17: 饰品品质权重 | C17: AccessoryPool_Legendary | D17: Legendary | E17: 15 | F17: 19 | G17: 3 | H17: 1.4 | I17: 1.2 | J17: 按具体饰品重复口径 | K17: 基础权重为0时不开放；唯一/上限达成则剔除 | L17: 商店饰品格 | M17: 品质层权重，用于幸运修正和波次开放。
A18: Shop_AccessoryQuality_Common_20_PLUS | B18: 饰品品质权重 | C18: AccessoryPool_Common | D18: Common | E18: 20 | F18: - | G18: 20 | H18: -0.4 | I18: 1 | J18: 按具体饰品重复口径 | K18: 基础权重为0时不开放；唯一/上限达成则剔除 | L18: 商店饰品格 | M18: 品质层权重，用于幸运修正和波次开放。
A19: Shop_AccessoryQuality_Rare_20_PLUS | B19: 饰品品质权重 | C19: AccessoryPool_Rare | D19: Rare | E19: 20 | F19: - | G19: 40 | H19: 0.4 | I19: 1.05 | J19: 按具体饰品重复口径 | K19: 基础权重为0时不开放；唯一/上限达成则剔除 | L19: 商店饰品格 | M19: 品质层权重，用于幸运修正和波次开放。
A20: Shop_AccessoryQuality_Epic_20_PLUS | B20: 饰品品质权重 | C20: AccessoryPool_Epic | D20: Epic | E20: 20 | F20: - | G20: 34 | H20: 0.9 | I20: 1.1 | J20: 按具体饰品重复口径 | K20: 基础权重为0时不开放；唯一/上限达成则剔除 | L20: 商店饰品格 | M20: 品质层权重，用于幸运修正和波次开放。
A21: Shop_AccessoryQuality_Legendary_20_PLUS | B21: 饰品品质权重 | C21: AccessoryPool_Legendary | D21: Legendary | E21: 20 | F21: - | G21: 6 | H21: 1.4 | I21: 1.2 | J21: 按具体饰品重复口径 | K21: 基础权重为0时不开放；唯一/上限达成则剔除 | L21: 商店饰品格 | M21: 品质层权重，用于幸运修正和波次开放。
A22: Shop_WeaponLevel_Lv1_01_04 | B22: 武器等级权重 | C22: WeaponPool_Lv1 | D22: Lv1 | E22: 1 | F22: 4 | G22: 100 | H22: -0.3 | I22: 1 | J22: 同名武器可重复，用于升级或新武器入口 | K22: 基础权重为0时不开放；武器槽满时只保留升级用途 | L22: 商店武器格 | M22: 等级层只控可见性，等级价格由武器等级表计算。
A23: Shop_WeaponLevel_Lv2_01_04 | B23: 武器等级权重 | C23: WeaponPool_Lv2 | D23: Lv2 | E23: 1 | F23: 4 | G23: 0 | H23: 0.3 | I23: 1 | J23: 同名武器可重复，用于升级或新武器入口 | K23: 基础权重为0时不开放；武器槽满时只保留升级用途 | L23: 商店武器格 | M23: 等级层只控可见性，等级价格由武器等级表计算。
A24: Shop_WeaponLevel_Lv3_01_04 | B24: 武器等级权重 | C24: WeaponPool_Lv3 | D24: Lv3 | E24: 1 | F24: 4 | G24: 0 | H24: 0.8 | I24: 1.05 | J24: 同名武器可重复，用于升级或新武器入口 | K24: 基础权重为0时不开放；武器槽满时只保留升级用途 | L24: 商店武器格 | M24: 等级层只控可见性，等级价格由武器等级表计算。
A25: Shop_WeaponLevel_Lv4_01_04 | B25: 武器等级权重 | C25: WeaponPool_Lv4 | D25: Lv4 | E25: 1 | F25: 4 | G25: 0 | H25: 1.2 | I25: 1.1 | J25: 同名武器可重复，用于升级或新武器入口 | K25: 基础权重为0时不开放；武器槽满时只保留升级用途 | L25: 商店武器格 | M25: 等级层只控可见性，等级价格由武器等级表计算。
A26: Shop_WeaponLevel_Lv1_05_09 | B26: 武器等级权重 | C26: WeaponPool_Lv1 | D26: Lv1 | E26: 5 | F26: 9 | G26: 80 | H26: -0.3 | I26: 1 | J26: 同名武器可重复，用于升级或新武器入口 | K26: 基础权重为0时不开放；武器槽满时只保留升级用途 | L26: 商店武器格 | M26: 等级层只控可见性，等级价格由武器等级表计算。
A27: Shop_WeaponLevel_Lv2_05_09 | B27: 武器等级权重 | C27: WeaponPool_Lv2 | D27: Lv2 | E27: 5 | F27: 9 | G27: 20 | H27: 0.3 | I27: 1 | J27: 同名武器可重复，用于升级或新武器入口 | K27: 基础权重为0时不开放；武器槽满时只保留升级用途 | L27: 商店武器格 | M27: 等级层只控可见性，等级价格由武器等级表计算。
A28: Shop_WeaponLevel_Lv3_05_09 | B28: 武器等级权重 | C28: WeaponPool_Lv3 | D28: Lv3 | E28: 5 | F28: 9 | G28: 0 | H28: 0.8 | I28: 1.05 | J28: 同名武器可重复，用于升级或新武器入口 | K28: 基础权重为0时不开放；武器槽满时只保留升级用途 | L28: 商店武器格 | M28: 等级层只控可见性，等级价格由武器等级表计算。
A29: Shop_WeaponLevel_Lv4_05_09 | B29: 武器等级权重 | C29: WeaponPool_Lv4 | D29: Lv4 | E29: 5 | F29: 9 | G29: 0 | H29: 1.2 | I29: 1.1 | J29: 同名武器可重复，用于升级或新武器入口 | K29: 基础权重为0时不开放；武器槽满时只保留升级用途 | L29: 商店武器格 | M29: 等级层只控可见性，等级价格由武器等级表计算。
A30: Shop_WeaponLevel_Lv1_10_14 | B30: 武器等级权重 | C30: WeaponPool_Lv1 | D30: Lv1 | E30: 10 | F30: 14 | G30: 55 | H30: -0.3 | I30: 1 | J30: 同名武器可重复，用于升级或新武器入口 | K30: 基础权重为0时不开放；武器槽满时只保留升级用途 | L30: 商店武器格 | M30: 等级层只控可见性，等级价格由武器等级表计算。
A31: Shop_WeaponLevel_Lv2_10_14 | B31: 武器等级权重 | C31: WeaponPool_Lv2 | D31: Lv2 | E31: 10 | F31: 14 | G31: 35 | H31: 0.3 | I31: 1 | J31: 同名武器可重复，用于升级或新武器入口 | K31: 基础权重为0时不开放；武器槽满时只保留升级用途 | L31: 商店武器格 | M31: 等级层只控可见性，等级价格由武器等级表计算。
A32: Shop_WeaponLevel_Lv3_10_14 | B32: 武器等级权重 | C32: WeaponPool_Lv3 | D32: Lv3 | E32: 10 | F32: 14 | G32: 10 | H32: 0.8 | I32: 1.05 | J32: 同名武器可重复，用于升级或新武器入口 | K32: 基础权重为0时不开放；武器槽满时只保留升级用途 | L32: 商店武器格 | M32: 等级层只控可见性，等级价格由武器等级表计算。
A33: Shop_WeaponLevel_Lv4_10_14 | B33: 武器等级权重 | C33: WeaponPool_Lv4 | D33: Lv4 | E33: 10 | F33: 14 | G33: 0 | H33: 1.2 | I33: 1.1 | J33: 同名武器可重复，用于升级或新武器入口 | K33: 基础权重为0时不开放；武器槽满时只保留升级用途 | L33: 商店武器格 | M33: 等级层只控可见性，等级价格由武器等级表计算。
... A37: Shop_WeaponLevel_Lv4_15_19 | B37: 武器等级权重 | C37: WeaponPool_Lv4 | D37: Lv4 | E37: 15 | F37: 19 | G37: 3 | H37: 1.2 | I37: 1.1 | J37: 同名武器可重复，用于升级或新武器入口 | K37: 基础权重为0时不开放；武器槽满时只保留升级用途 | L37: 商店武器格 | M37: 等级层只控可见性，等级价格由武器等级表计算。
A38: Shop_WeaponLevel_Lv1_20_PLUS | B38: 武器等级权重 | C38: WeaponPool_Lv1 | D38: Lv1 | E38: 20 | F38: - | G38: 25 | H38: -0.3 | I38: 1 | J38: 同名武器可重复，用于升级或新武器入口 | K38: 基础权重为0时不开放；武器槽满时只保留升级用途 | L38: 商店武器格 | M38: 等级层只控可见性，等级价格由武器等级表计算。
A39: Shop_WeaponLevel_Lv2_20_PLUS | B39: 武器等级权重 | C39: WeaponPool_Lv2 | D39: Lv2 | E39: 20 | F39: - | G39: 35 | H39: 0.3 | I39: 1 | J39: 同名武器可重复，用于升级或新武器入口 | K39: 基础权重为0时不开放；武器槽满时只保留升级用途 | L39: 商店武器格 | M39: 等级层只控可见性，等级价格由武器等级表计算。
A40: Shop_WeaponLevel_Lv3_20_PLUS | B40: 武器等级权重 | C40: WeaponPool_Lv3 | D40: Lv3 | E40: 20 | F40: - | G40: 32 | H40: 0.8 | I40: 1.05 | J40: 同名武器可重复，用于升级或新武器入口 | K40: 基础权重为0时不开放；武器槽满时只保留升级用途 | L40: 商店武器格 | M40: 等级层只控可见性，等级价格由武器等级表计算。
A41: Shop_WeaponLevel_Lv4_20_PLUS | B41: 武器等级权重 | C41: WeaponPool_Lv4 | D41: Lv4 | E41: 20 | F41: - | G41: 8 | H41: 1.2 | I41: 1.1 | J41: 同名武器可重复，用于升级或新武器入口 | K41: 基础权重为0时不开放；武器槽满时只保留升级用途 | L41: 商店武器格 | M41: 等级层只控可见性，等级价格由武器等级表计算。
A42: Shop_Accessory_C_DamageCharm | B42: 饰品 | C42: Accessory_C_DamageCharm | D42: Common | E42: 1 | F42: - | G42: 100 | H42: -0.4 | I42: 1 | J42: 可重复 | K42: 唯一或达到适量上限时剔除；其余允许重复 | L42: 商店 | M42: 具体饰品条目，最终可见性还要乘以品质层权重。
A43: Shop_Accessory_C_LightTrigger | B43: 饰品 | C43: Accessory_C_LightTrigger | D43: Common | E43: 1 | F43: - | G43: 100 | H43: -0.4 | I43: 1 | J43: 可重复 | K43: 唯一或达到适量上限时剔除；其余允许重复 | L43: 商店 | M43: 具体饰品条目，最终可见性还要乘以品质层权重。
A44: Shop_Accessory_C_PaddedVest | B44: 饰品 | C44: Accessory_C_PaddedVest | D44: Common | E44: 1 | F44: - | G44: 95 | H44: -0.4 | I44: 1 | J44: 可重复 | K44: 唯一或达到适量上限时剔除；其余允许重复 | L44: 商店 | M44: 具体饰品条目，最终可见性还要乘以品质层权重。
A45: Shop_Accessory_C_FirstAidKit | B45: 饰品 | C45: Accessory_C_FirstAidKit | D45: Common | E45: 1 | F45: - | G45: 80 | H45: -0.4 | I45: 1 | J45: 可重复 | K45: 唯一或达到适量上限时剔除；其余允许重复 | L45: 商店 | M45: 具体饰品条目，最终可见性还要乘以品质层权重。
A46: Shop_Accessory_C_SpringLace | B46: 饰品 | C46: Accessory_C_SpringLace | D46: Common | E46: 1 | F46: - | G46: 80 | H46: -0.4 | I46: 1 | J46: 可重复 | K46: 唯一或达到适量上限时剔除；其余允许重复 | L46: 商店 | M46: 具体饰品条目，最终可见性还要乘以品质层权重。
A47: Shop_Accessory_C_MagnetRing | B47: 饰品 | C47: Accessory_C_MagnetRing | D47: Common | E47: 1 | F47: - | G47: 75 | H47: -0.4 | I47: 1 | J47: 可重复 | K47: 唯一或达到适量上限时剔除；其余允许重复 | L47: 商店 | M47: 具体饰品条目，最终可见性还要乘以品质层权重。
A48: Shop_Accessory_C_LuckyCoin | B48: 饰品 | C48: Accessory_C_LuckyCoin | D48: Common | E48: 1 | F48: - | G48: 45 | H48: -0.4 | I48: 1 | J48: 可重复 | K48: 唯一或达到适量上限时剔除；其余允许重复 | L48: 商店 | M48: 具体饰品条目，最终可见性还要乘以品质层权重。
A49: Shop_Accessory_C_ShortScope | B49: 饰品 | C49: Accessory_C_ShortScope | D49: Common | E49: 1 | F49: - | G49: 70 | H49: -0.4 | I49: 1 | J49: 可重复 | K49: 唯一或达到适量上限时剔除；其余允许重复 | L49: 商店 | M49: 具体饰品条目，最终可见性还要乘以品质层权重。
... A89: Shop_Weapon_GreatAxe | B89: 武器 | C89: Weapon_GreatAxe | D89: 强力武器 | E89: 5 | F89: - | G89: 35 | H89: 0 | I89: 1.2 | J89: 同名武器可重复，用于新武器或升级入口 | K89: 武器槽满时只保留升级用途；强力武器受自身开放波次限制 | L89: 商店武器格 | M89: 具体武器条目，等级可见性还要乘以武器等级层权重。

Sheet 10_掉落奖励池
A1: 奖励池ID | B1: 来源类型 | C1: 来源ID | D1: 击杀经验 | E1: 奖励掉落率 | F1: 掉落率上限 | G1: 产物类型 | H1: 产物ID或池 | I1: 产物数量/价值 | J1: 基础权重 | K1: 幸运系数 | L1: 品质/等级权重 | M1: 期望收益 | N1: 备注
A2: Drop_Enemy_SkeletonEnemy | B2: 普通怪 | C2: SkeletonEnemy | D2: 1 | E2: 0.18 | F2: 0.35 | G2: 奖励池 | H2: RewardPool_Normal | I2: 1 | J2: 100 | K2: 0.3 | L2: 金币100 | M2: =IF(AND(ISNUMBER(E2),ISNUMBER(I2)),ROUND(E2*I2,2),IF(ISNUMBER(J2),J2&" 权重","按入口")) -> 0.18 | N2: 普通近战基准掉落。
A3: Drop_Enemy_EvilSlimeEnemy | B3: 快速怪 | C3: EvilSlimeEnemy | D3: 1 | E3: 0.12 | F3: 0.25 | G3: 奖励池 | H3: RewardPool_Normal | I3: 1 | J3: 100 | K3: 0.3 | L3: 金币100 | M3: =IF(AND(ISNUMBER(E3),ISNUMBER(I3)),ROUND(E3*I3,2),IF(ISNUMBER(J3),J3&" 权重","按入口")) -> 0.12 | N3: 快速怪数量高，掉率保守。
A4: Drop_Enemy_WormEnemy | B4: 普通远程 | C4: WormEnemy | D4: 1 | E4: 0.18 | F4: 0.35 | G4: 奖励池 | H4: RewardPool_Normal | I4: 1 | J4: 100 | K4: 0.3 | L4: 金币100 | M4: =IF(AND(ISNUMBER(E4),ISNUMBER(I4)),ROUND(E4*I4,2),IF(ISNUMBER(J4),J4&" 权重","按入口")) -> 0.18 | N4: 低频远程风筝怪。
A5: Drop_Enemy_FlyForestEnemy | B5: 普通远程 | C5: FlyForestEnemy | D5: 1 | E5: 0.18 | F5: 0.35 | G5: 奖励池 | H5: RewardPool_Normal | I5: 1 | J5: 100 | K5: 0.3 | L5: 金币100 | M5: =IF(AND(ISNUMBER(E5),ISNUMBER(I5)),ROUND(E5*I5,2),IF(ISNUMBER(J5),J5&" 权重","按入口")) -> 0.18 | N5: 标准远程风筝怪。
A6: Drop_Enemy_EvilEyeEnemy | B6: 特殊远程 | C6: EvilEyeEnemy | D6: 1 | E6: 0.18 | F6: 0.35 | G6: 奖励池 | H6: RewardPool_Normal | I6: 1 | J6: 100 | K6: 0.3 | L6: 金币100 | M6: =IF(AND(ISNUMBER(E6),ISNUMBER(I6)),ROUND(E6*I6,2),IF(ISNUMBER(J6),J6&" 权重","按入口")) -> 0.18 | N6: 脆皮高威胁远程不天然提高奖励。
A7: Drop_Enemy_SkeletonMeteorhammerEnemy | B7: 重型怪 | C7: SkeletonMeteorhammerEnemy | D7: 2 | E7: 0.3 | F7: 0.6 | G7: 奖励池 | H7: RewardPool_Heavy | I7: 1 | J7: 100 | K7: 0.5 | L7: 金币90 / 小宝箱10 | M7: =IF(AND(ISNUMBER(E7),ISNUMBER(I7)),ROUND(E7*I7,2),IF(ISNUMBER(J7),J7&" 权重","按入口")) -> 0.3 | N7: 中距离重型近战。
A8: Drop_Enemy_SkeletonMeteorhammer2Enemy | B8: 重型怪 | C8: SkeletonMeteorhammer2Enemy | D8: 2 | E8: 0.32 | F8: 0.6 | G8: 奖励池 | H8: RewardPool_Heavy | I8: 1 | J8: 100 | K8: 0.5 | L8: 金币90 / 小宝箱10 | M8: =IF(AND(ISNUMBER(E8),ISNUMBER(I8)),ROUND(E8*I8,2),IF(ISNUMBER(J8),J8&" 权重","按入口")) -> 0.32 | N8: 二型覆盖更危险，掉率略高。
A9: Drop_Enemy_BlueGolemEnemy | B9: 重型怪 | C9: BlueGolemEnemy | D9: 2 | E9: 0.35 | F9: 0.6 | G9: 奖励池 | H9: RewardPool_Heavy | I9: 1 | J9: 100 | K9: 0.5 | L9: 金币90 / 小宝箱10 | M9: =IF(AND(ISNUMBER(E9),ISNUMBER(I9)),ROUND(E9*I9,2),IF(ISNUMBER(J9),J9&" 权重","按入口")) -> 0.35 | N9: 冲锋重型怪。
A10: Drop_Enemy_OrangeGolemEnemy | B10: 精英怪 | C10: OrangeGolemEnemy | D10: 4 | E10: 1 | F10: 1 | G10: 奖励池 | H10: RewardPool_Elite | I10: 1 | J10: 100 | K10: 0.8 | L10: 金币70 / 小宝箱30 | M10: =IF(AND(ISNUMBER(E10),ISNUMBER(I10)),ROUND(E10*I10,2),IF(ISNUMBER(J10),J10&" 权重","按入口")) -> 1 | N10: 高压重型/准精英，稳定给奖励。
A11: Drop_Enemy_MechaStoneBossEnemy | B11: Boss | C11: MechaStoneBossEnemy | D11: 12 | E11: 1 | F11: 1 | G11: 固定奖励 | H11: RewardPool_Boss | I11: 选择1项 | J11: 100 | K11: 0 | L11: Boss奖励100 | M11: =IF(AND(ISNUMBER(E11),ISNUMBER(I11)),ROUND(E11*I11,2),IF(ISNUMBER(J11),J11&" 权重","按入口")) -> 100 权重 | N11: Boss奖励不提高次数，幸运只影响内部品质。
A12: Pool_Normal_Gold | B12: 奖励池条目 | C12: RewardPool_Normal | D12: 0 | E12: - | F12: - | G12: 金币拾取物 | H12: GoldPickup | I12: 1 | J12: 100 | K12: 0.3 | L12: 金币100 | M12: =IF(AND(ISNUMBER(E12),ISNUMBER(I12)),ROUND(E12*I12,2),IF(ISNUMBER(J12),J12&" 权重","按入口")) -> 100 权重 | N12: 普通奖励池只掉金币。
A13: Pool_Heavy_Gold | B13: 奖励池条目 | C13: RewardPool_Heavy | D13: 0 | E13: - | F13: - | G13: 金币拾取物 | H13: GoldPickup | I13: 1 | J13: 90 | K13: 0.3 | L13: 金币90 | M13: =IF(AND(ISNUMBER(E13),ISNUMBER(I13)),ROUND(E13*I13,2),IF(ISNUMBER(J13),J13&" 权重","按入口")) -> 90 权重 | N13: 重型奖励池金币项。
A14: Pool_Heavy_Chest | B14: 奖励池条目 | C14: RewardPool_Heavy | D14: 0 | E14: - | F14: - | G14: 小宝箱 | H14: Chest_Small | I14: 1 | J14: 10 | K14: 0.8 | L14: 小宝箱10 | M14: =IF(AND(ISNUMBER(E14),ISNUMBER(I14)),ROUND(E14*I14,2),IF(ISNUMBER(J14),J14&" 权重","按入口")) -> 10 权重 | N14: 重型奖励池少量宝箱入口。
A15: Pool_Elite_GoldPack | B15: 奖励池条目 | C15: RewardPool_Elite | D15: 0 | E15: - | F15: - | G15: 金币包 | H15: GoldPack_Medium | I15: 8 | J15: 70 | K15: 0.3 | L15: 金币包70 | M15: =IF(AND(ISNUMBER(E15),ISNUMBER(I15)),ROUND(E15*I15,2),IF(ISNUMBER(J15),J15&" 权重","按入口")) -> 70 权重 | N15: 精英奖励中的保底经济项。
A16: Pool_Elite_Chest | B16: 奖励池条目 | C16: RewardPool_Elite | D16: 0 | E16: - | F16: - | G16: 小宝箱 | H16: Chest_Small | I16: 1 | J16: 30 | K16: 0.8 | L16: 小宝箱30 | M16: =IF(AND(ISNUMBER(E16),ISNUMBER(I16)),ROUND(E16*I16,2),IF(ISNUMBER(J16),J16&" 权重","按入口")) -> 30 权重 | N16: 精英奖励中的惊喜项。
A17: Pool_SmallChest_Gold | B17: 宝箱条目 | C17: Chest_Small | D17: 0 | E17: - | F17: - | G17: 金币包 | H17: GoldPack_Small | I17: 12 | J17: 55 | K17: 0.3 | L17: 金币包55 | M17: =IF(AND(ISNUMBER(E17),ISNUMBER(I17)),ROUND(E17*I17,2),IF(ISNUMBER(J17),J17&" 权重","按入口")) -> 55 权重 | N17: 小宝箱默认内容。
A18: Pool_SmallChest_CommonAccessory | B18: 宝箱条目 | C18: Chest_Small | D18: 0 | E18: - | F18: - | G18: 饰品池 | H18: AccessoryPool_Common | I18: 1 | J18: 25 | K18: -0.4 | L18: Common 25 | M18: =IF(AND(ISNUMBER(E18),ISNUMBER(I18)),ROUND(E18*I18,2),IF(ISNUMBER(J18),J18&" 权重","按入口")) -> 25 权重 | N18: 小宝箱普通饰品入口。
A19: Pool_SmallChest_RareAccessory | B19: 宝箱条目 | C19: Chest_Small | D19: 0 | E19: - | F19: - | G19: 饰品池 | H19: AccessoryPool_Rare | I19: 1 | J19: 15 | K19: 1 | L19: Rare 15 | M19: =IF(AND(ISNUMBER(E19),ISNUMBER(I19)),ROUND(E19*I19,2),IF(ISNUMBER(J19),J19&" 权重","按入口")) -> 15 权重 | N19: 幸运提高 Rare+ 权重。
A20: Pool_SmallChest_Weapon | B20: 宝箱条目 | C20: Chest_Small | D20: 0 | E20: - | F20: - | G20: 武器池 | H20: WeaponPool_Lv1_Lv2 | I20: 1 | J20: 5 | K20: 0.5 | L20: Lv1/Lv2 5 | M20: =IF(AND(ISNUMBER(E20),ISNUMBER(I20)),ROUND(E20*I20,2),IF(ISNUMBER(J20),J20&" 权重","按入口")) -> 5 权重 | N20: 只提供低档武器惊喜。
A21: Pool_Boss_Weapon | B21: Boss奖励条目 | C21: RewardPool_Boss | D21: 0 | E21: - | F21: - | G21: 武器选择 | H21: WeaponPool_HighLevel | I21: 1 | J21: 35 | K21: 0.6 | L21: Lv2+ 35 | M21: =IF(AND(ISNUMBER(E21),ISNUMBER(I21)),ROUND(E21*I21,2),IF(ISNUMBER(J21),J21&" 权重","按入口")) -> 35 权重 | N21: Boss奖励可提供高等级武器选择。
A22: Pool_Boss_Accessory | B22: Boss奖励条目 | C22: RewardPool_Boss | D22: 0 | E22: - | F22: - | G22: 饰品选择 | H22: AccessoryPool_RarePlus | I22: 1 | J22: 35 | K22: 1 | L22: Rare+ 35 | M22: =IF(AND(ISNUMBER(E22),ISNUMBER(I22)),ROUND(E22*I22,2),IF(ISNUMBER(J22),J22&" 权重","按入口")) -> 35 权重 | N22: Boss奖励主要构筑入口。
A23: Pool_Boss_Upgrade | B23: Boss奖励条目 | C23: RewardPool_Boss | D23: 0 | E23: - | F23: - | G23: 升级选择 | H23: UpgradeCardChoice | I23: 1 | J23: 20 | K23: 0 | L23: 升级选择20 | M23: =IF(AND(ISNUMBER(E23),ISNUMBER(I23)),ROUND(E23*I23,2),IF(ISNUMBER(J23),J23&" 权重","按入口")) -> 20 权重 | N23: 不进入普通升级卡数量上限，因为升级卡不限制次数。
A24: Pool_Boss_Gold | B24: Boss奖励条目 | C24: RewardPool_Boss | D24: 0 | E24: - | F24: - | G24: 金币包 | H24: GoldPack_Large | I24: 40 | J24: 10 | K24: 0.3 | L24: 金币包10 | M24: =IF(AND(ISNUMBER(E24),ISNUMBER(I24)),ROUND(E24*I24,2),IF(ISNUMBER(J24),J24&" 权重","按入口")) -> 10 权重 | N24: 低权重经济兜底。

Sheet 11_校验汇总
A1: 校验ID | B1: 波次 | C1: 标准构筑 | D1: 玩家状态 | E1: 武器状态 | F1: 饰品状态 | G1: 有效单体DPS | H1: 群体等效DPS | I1: 瞬时EHP | J1: 持续生存 | K1: 普通怪击杀时间 | L1: 重型/精英/Boss击杀时间 | M1: 清场压力 | N1: 经济偏差 | O1: 问题归因 | P1: 调整建议
A2: Check_Wave05 | B2: 5 | C2: 普通输出构筑 | D2: Lv6-7；升级卡5-6；累计金币120-180；购买4-6 | E2: 1把主力Lv2，并有副武器或关键饰品 | F2: 2-4件 | G2: 90 | H2: 200 | I2: 145 | J2: 5 | K2: 目标0.7-1.3秒 | L2: 重型3.0-5.0秒；精英8-14秒；Boss不出现 | M2: =IFERROR("清场需求 "&VLOOKUP("Wave_005",'08_波次'!$A:$P,9,FALSE)&"；需求/群体 "&TEXT(VLOOKUP("Wave_005",'08_波次'!$A:$P,9,FALSE)/H2,"0.00x"),"") -> 清场需求 164；需求/群体 0.82x | N2: 累计金币与购买量应进入取舍区间 | O2: 待实测回填 | P2: 若清场过慢，优先调普通/重型数量和波次生命池。
A3: Check_Wave10 | B3: 10 | C3: 成型前构筑 | D3: Lv10-12；升级卡9-11；累计金币360-540；购买9-13 | E3: 1把主力Lv3，副武器至少Lv2 | F3: 5-8件 | G3: 240 | H3: 550 | I3: 235 | J3: 4.5 | K3: 目标0.6-1.1秒 | L3: 重型3.5-5.5秒；精英10-18秒；Boss35-55秒 | M3: =IFERROR("清场需求 "&VLOOKUP("Wave_010",'08_波次'!$A:$P,9,FALSE)&"；需求/群体 "&TEXT(VLOOKUP("Wave_010",'08_波次'!$A:$P,9,FALSE)/H3,"0.00x"),"") -> 清场需求 583；需求/群体 1.06x | N3: 刷新4-8次后应能看到明确升级目标 | O3: 待实测回填 | P3: 若Boss过短，增加Boss生命或阶段；若小怪堆积，先降密度峰值。
A4: Check_Wave15 | B4: 15 | C4: 后期过渡构筑 | D4: Lv15-17；升级卡14-16；累计金币750-1100；购买16-22 | E4: 主力Lv4或双Lv3，副武器Lv2-Lv3 | F4: 9-13件 | G4: 525 | H4: 1250 | I4: 400 | J4: 4 | K4: 目标0.5-1.0秒 | L4: 重型4.0-6.5秒；精英12-22秒；Boss45-70秒 | M4: =IFERROR("清场需求 "&VLOOKUP("Wave_015",'08_波次'!$A:$P,9,FALSE)&"；需求/群体 "&TEXT(VLOOKUP("Wave_015",'08_波次'!$A:$P,9,FALSE)/H4,"0.00x"),"") -> 清场需求 1769；需求/群体 1.42x | N4: 购买和刷新都应有压力，不能稳定全买 | O4: 待实测回填 | P4: 若后期威胁不足，优先提高精英/Boss节奏和生命池。
A5: Check_Wave20 | B5: 20 | C5: 终局普通构筑 | D5: Lv20-23；升级卡19-22；累计金币1300-1900；购买24-32 | E5: 主力Lv4，至少2把副武器Lv3左右 | F5: 13-18件 | G5: 975 | H5: 2500 | I5: 650 | J5: 3.5 | K5: 目标0.4-0.9秒 | L5: 重型4.5-7.5秒；精英15-28秒；Boss60-90秒 | M5: =IFERROR("清场需求 "&VLOOKUP("Wave_020",'08_波次'!$A:$P,9,FALSE)&"；需求/群体 "&TEXT(VLOOKUP("Wave_020",'08_波次'!$A:$P,9,FALSE)/H5,"0.00x"),"") -> 清场需求 5600；需求/群体 2.24x | N5: 当前留存60-160，刷新12-22次 | O5: 待实测回填 | P5: 若终局只能堆数量，应改成Boss/精英/远程组合压力。
